[
  {
    "code": "Jn8JCmTA0Ex3X2zgBtyBW6",
    "url": "https://chat.whatsapp.com/Jn8JCmTA0Ex3X2zgBtyBW6"
  },
  {
    "code": "Hy6C0NNx9QLFIBF7L2WaBT",
    "url": "https://chat.whatsapp.com/invite/Hy6C0NNx9QLFIBF7L2WaBT"
  },
  {
    "code": "Lmha8q2hz0a1585E2g8B0z",
    "url": "https://chat.whatsapp.com/invite/Lmha8q2hz0a1585E2g8B0z"
  },
  {
    "code": "FxLDfyz5HLJ936ghvwt0qJ",
    "url": "https://chat.whatsapp.com/FxLDfyz5HLJ936ghvwt0qJ"
  },
  {
    "code": "E3WKF6paTPII1FhFLpZn6N",
    "url": "https://chat.whatsapp.com/invite/E3WKF6paTPII1FhFLpZn6N"
  },
  {
    "code": "DstVuSK7k4O5XPueb4VTrW",
    "url": "https://chat.whatsapp.com/invite/DstVuSK7k4O5XPueb4VTrW"
  },
  {
    "code": "GBPIbBdreruDHxa11TvBjC",
    "url": "https://chat.whatsapp.com/invite/GBPIbBdreruDHxa11TvBjC"
  },
  {
    "code": "KVHgoaCEuHu4E7vxDdrHuf",
    "url": "https://chat.whatsapp.com/invite/KVHgoaCEuHu4E7vxDdrHuf"
  },
  {
    "code": "DWO4vwJcBwe3xW6itviRHM",
    "url": "https://chat.whatsapp.com/invite/DWO4vwJcBwe3xW6itviRHM"
  },
  {
    "code": "F4uO36XoB2qJ43Vm9NfMIW",
    "url": "https://chat.whatsapp.com/invite/F4uO36XoB2qJ43Vm9NfMIW"
  },
  {
    "code": "CKWRQ2ZOR5y3MQMEH5bggh",
    "url": "https://chat.whatsapp.com/invite/CKWRQ2ZOR5y3MQMEH5bggh"
  },
  {
    "code": "EsVxykHITm5GQXNJKChYhc",
    "url": "https://chat.whatsapp.com/invite/EsVxykHITm5GQXNJKChYhc"
  },
  {
    "code": "BDGDPg6kKxV1mSJ7SVuN5l",
    "url": "https://chat.whatsapp.com/invite/BDGDPg6kKxV1mSJ7SVuN5l"
  },
  {
    "code": "EWDsc4wc8vXBPords58na6",
    "url": "https://chat.whatsapp.com/invite/EWDsc4wc8vXBPords58na6"
  },
  {
    "code": "BukztKgsRHq4ziJRgm9lVh",
    "url": "https://chat.whatsapp.com/BukztKgsRHq4ziJRgm9lVh"
  },
  {
    "code": "DXFaUaWlhCp2N5jigwhEHU",
    "url": "https://chat.whatsapp.com/DXFaUaWlhCp2N5jigwhEHU"
  },
  {
    "code": "CSYMnwp4XjuBIFlnQWKa2R",
    "url": "https://chat.whatsapp.com/CSYMnwp4XjuBIFlnQWKa2R"
  },
  {
    "code": "EaSiCWGQJYGKdMNiSLPgYA",
    "url": "https://chat.whatsapp.com/EaSiCWGQJYGKdMNiSLPgYA"
  },
  {
    "code": "FQaPpPA5vjQJJUvmTrfKFC",
    "url": "https://chat.whatsapp.com/FQaPpPA5vjQJJUvmTrfKFC"
  },
  {
    "code": "IxWZ3MsfoS59bFdog9MpJK",
    "url": "https://chat.whatsapp.com/invite/IxWZ3MsfoS59bFdog9MpJK"
  },
  {
    "code": "LCUchRcgYZpIomOdjNiyCx",
    "url": "https://chat.whatsapp.com/invite/LCUchRcgYZpIomOdjNiyCx"
  },
  {
    "code": "FsxKrv9YD0i6X4CQRj1VfA",
    "url": "https://chat.whatsapp.com/invite/FsxKrv9YD0i6X4CQRj1VfA"
  },
  {
    "code": "JmZSra08Jcr0jDjyKoUZ5H",
    "url": "https://chat.whatsapp.com/invite/JmZSra08Jcr0jDjyKoUZ5H"
  },
  {
    "code": "LVVvodYtXI5Ir0zUfSfDE9",
    "url": "https://chat.whatsapp.com/invite/LVVvodYtXI5Ir0zUfSfDE9"
  },
  {
    "code": "DMCqiZL1qlHKiS5QmUjybN",
    "url": "https://chat.whatsapp.com/invite/DMCqiZL1qlHKiS5QmUjybN"
  },
  {
    "code": "JaVoiH9EHb49jJfVC5rEE4",
    "url": "https://chat.whatsapp.com/invite/JaVoiH9EHb49jJfVC5rEE4"
  },
  {
    "code": "HC6mhCF3P7O8HPV3X6mDvy",
    "url": "https://chat.whatsapp.com/invite/HC6mhCF3P7O8HPV3X6mDvy"
  },
  {
    "code": "IXmBi9Nlg8sFTqwRnhZBYg",
    "url": "https://chat.whatsapp.com/invite/IXmBi9Nlg8sFTqwRnhZBYg"
  },
  {
    "code": "EGZXMUn5ucf6dJtM5OeJwd",
    "url": "https://chat.whatsapp.com/invite/EGZXMUn5ucf6dJtM5OeJwd"
  },
  {
    "code": "F8qfsYBHDjA4eJ7nNLhToG",
    "url": "https://chat.whatsapp.com/invite/F8qfsYBHDjA4eJ7nNLhToG"
  },
  {
    "code": "GFQwotqTDk3L5zgNbn4l45",
    "url": "https://chat.whatsapp.com/invite/GFQwotqTDk3L5zgNbn4l45"
  },
  {
    "code": "Ijx2k9qwJhrL7ZvJGTH1rx",
    "url": "https://chat.whatsapp.com/invite/Ijx2k9qwJhrL7ZvJGTH1rx"
  },
  {
    "code": "Ftsy3wXvR2dLGY8Lr82Mqr",
    "url": "https://chat.whatsapp.com/invite/Ftsy3wXvR2dLGY8Lr82Mqr"
  },
  {
    "code": "EchY335r8a479XqO0cQL8g",
    "url": "https://chat.whatsapp.com/invite/EchY335r8a479XqO0cQL8g"
  },
  {
    "code": "DFKrRCLvBAXGRkychNt0hv",
    "url": "https://chat.whatsapp.com/invite/DFKrRCLvBAXGRkychNt0hv"
  },
  {
    "code": "H0zNphtZjXlILlbL6mSpJ4",
    "url": "https://chat.whatsapp.com/invite/H0zNphtZjXlILlbL6mSpJ4"
  },
  {
    "code": "G16kvarfXze1RlmJyeuy47",
    "url": "https://chat.whatsapp.com/invite/G16kvarfXze1RlmJyeuy47"
  },
  {
    "code": "JanuhLFmmnsEcGy1UqBLgL",
    "url": "https://chat.whatsapp.com/invite/JanuhLFmmnsEcGy1UqBLgL"
  },
  {
    "code": "LTwMf4wlI0A5EPOkNUKqbM",
    "url": "https://chat.whatsapp.com/invite/LTwMf4wlI0A5EPOkNUKqbM"
  },
  {
    "code": "CyO6dLcNEV0BHLfQKGJtiz",
    "url": "https://chat.whatsapp.com/CyO6dLcNEV0BHLfQKGJtiz"
  },
  {
    "code": "1F2NSdRGmkX06HTHb9QE8I",
    "url": "https://chat.whatsapp.com/invite/1F2NSdRGmkX06HTHb9QE8I"
  },
  {
    "code": "CXcqkhHONbiHSaGkQkcR6E",
    "url": "https://chat.whatsapp.com/CXcqkhHONbiHSaGkQkcR6E"
  },
  {
    "code": "JqqB3RakPl78EOsGNiZAKp",
    "url": "https://chat.whatsapp.com/JqqB3RakPl78EOsGNiZAKp"
  },
  {
    "code": "Bcp3tVHuzQMAFwbZ7chxWI",
    "url": "https://chat.whatsapp.com/Bcp3tVHuzQMAFwbZ7chxWI"
  },
  {
    "code": "LISgufr1ZBm9T7lx5NiFre",
    "url": "https://chat.whatsapp.com/LISgufr1ZBm9T7lx5NiFre"
  },
  {
    "code": "84fksdSRq5e7QS4WQUmlHn",
    "url": "https://chat.whatsapp.com/invite/84fksdSRq5e7QS4WQUmlHn"
  },
  {
    "code": "BnEs5Y2zgRpBEfzgeNQHEg",
    "url": "https://chat.whatsapp.com/BnEs5Y2zgRpBEfzgeNQHEg"
  },
  {
    "code": "BR9Io94DCckKgfm3hIRFkD",
    "url": "https://chat.whatsapp.com/invite/BR9Io94DCckKgfm3hIRFkD"
  },
  {
    "code": "FUg9hIAApg02Gdk2RTxlCj",
    "url": "https://chat.whatsapp.com/FUg9hIAApg02Gdk2RTxlCj"
  },
  {
    "code": "BqoPr6VRrBV1aBdgNhooNw",
    "url": "https://chat.whatsapp.com/BqoPr6VRrBV1aBdgNhooNw"
  },
  {
    "code": "0V5ZyZytAjl0hVd0XD7Wdg",
    "url": "https://chat.whatsapp.com/invite/0V5ZyZytAjl0hVd0XD7Wdg"
  },
  {
    "code": "IaFPg0mNxNR9hzVe2bqwYb",
    "url": "https://chat.whatsapp.com/IaFPg0mNxNR9hzVe2bqwYb"
  },
  {
    "code": "BU8sTTTMAgiKHJDEFMXtvm",
    "url": "https://chat.whatsapp.com/BU8sTTTMAgiKHJDEFMXtvm"
  },
  {
    "code": "HkdTYEmDsJQCr6IZ2V4sIY",
    "url": "https://chat.whatsapp.com/HkdTYEmDsJQCr6IZ2V4sIY"
  },
  {
    "code": "G6wm1LqzrQQKqpTrh5r8Qd",
    "url": "https://chat.whatsapp.com/G6wm1LqzrQQKqpTrh5r8Qd"
  },
  {
    "code": "INw0p62qJMNBiWC8Hgu8Uz",
    "url": "https://chat.whatsapp.com/INw0p62qJMNBiWC8Hgu8Uz"
  },
  {
    "code": "Do4ozY7eH4EErhtqm3X1aX",
    "url": "https://chat.whatsapp.com/Do4ozY7eH4EErhtqm3X1aX"
  },
  {
    "code": "JzQqYtX3nEZLrjTPy1YdWZ",
    "url": "https://chat.whatsapp.com/JzQqYtX3nEZLrjTPy1YdWZ"
  },
  {
    "code": "B6aalDVhlulEAQ5w1dBczl",
    "url": "https://chat.whatsapp.com/B6aalDVhlulEAQ5w1dBczl"
  },
  {
    "code": "LAiEblxGR8lISlcU85Bjz1",
    "url": "https://chat.whatsapp.com/LAiEblxGR8lISlcU85Bjz1"
  },
  {
    "code": "BSiqeVRwkMKJpLMxLzBOzw",
    "url": "https://chat.whatsapp.com/BSiqeVRwkMKJpLMxLzBOzw"
  },
  {
    "code": "FkxU2K0csOZ9If847Ujzh1",
    "url": "https://chat.whatsapp.com/FkxU2K0csOZ9If847Ujzh1"
  },
  {
    "code": "ECo6xn0IAKgKAg7AkYtDfq",
    "url": "https://chat.whatsapp.com/ECo6xn0IAKgKAg7AkYtDfq"
  },
  {
    "code": "LvoyMOMiPKp32ysB3ns3ny",
    "url": "https://chat.whatsapp.com/LvoyMOMiPKp32ysB3ns3ny"
  },
  {
    "code": "CQwIlVCLPpxBS9OpK0bAWF",
    "url": "https://chat.whatsapp.com/CQwIlVCLPpxBS9OpK0bAWF"
  },
  {
    "code": "CkqCEnlGNzBBJAbZHQIQ9c",
    "url": "https://chat.whatsapp.com/CkqCEnlGNzBBJAbZHQIQ9c"
  },
  {
    "code": "IWDUZ0zg9ppDXnsRKXQdM3",
    "url": "https://chat.whatsapp.com/IWDUZ0zg9ppDXnsRKXQdM3"
  },
  {
    "code": "DnbGfjHbc0qENT0N9h3wRF",
    "url": "https://chat.whatsapp.com/DnbGfjHbc0qENT0N9h3wRF"
  },
  {
    "code": "3aF8l9ECQTM5bDcRkWRFIo",
    "url": "https://chat.whatsapp.com/invite/3aF8l9ECQTM5bDcRkWRFIo"
  },
  {
    "code": "2s7LSLt2D7wBcvpreiOXhA",
    "url": "https://chat.whatsapp.com/invite/2s7LSLt2D7wBcvpreiOXhA"
  },
  {
    "code": "6CCUEtrVYoRFFUXnVnyUuE",
    "url": "https://chat.whatsapp.com/invite/6CCUEtrVYoRFFUXnVnyUuE"
  },
  {
    "code": "FuV4skqyEQeIungVzGYLbv",
    "url": "https://chat.whatsapp.com/FuV4skqyEQeIungVzGYLbv"
  },
  {
    "code": "GFdvirKpz8KGdEbUM9Wtle",
    "url": "https://chat.whatsapp.com/invite/GFdvirKpz8KGdEbUM9Wtle"
  },
  {
    "code": "2ZFmQrZjlVEHcT3IrxPUvL",
    "url": "https://chat.whatsapp.com/invite/2ZFmQrZjlVEHcT3IrxPUvL"
  },
  {
    "code": "I45wZ0LBIkp7BVxWugTCqe",
    "url": "https://chat.whatsapp.com/I45wZ0LBIkp7BVxWugTCqe"
  },
  {
    "code": "GpfZXOUSWCQ45An2YYVzbs",
    "url": "https://chat.whatsapp.com/GpfZXOUSWCQ45An2YYVzbs"
  },
  {
    "code": "DjfGHgBi7M59hwSUuw3k9v",
    "url": "https://chat.whatsapp.com/DjfGHgBi7M59hwSUuw3k9v"
  },
  {
    "code": "Cpnkq2Bwzkm7qhlKFjVLPU",
    "url": "https://chat.whatsapp.com/Cpnkq2Bwzkm7qhlKFjVLPU"
  },
  {
    "code": "466VHOXUVawD69rZk1FX7T",
    "url": "https://chat.whatsapp.com/466VHOXUVawD69rZk1FX7T"
  },
  {
    "code": "CyA0FGvIZm0IpUmpfR1EP1",
    "url": "https://chat.whatsapp.com/CyA0FGvIZm0IpUmpfR1EP1"
  },
  {
    "code": "LXjEr1qRPBdILrGtXkc9lf",
    "url": "https://chat.whatsapp.com/invite/LXjEr1qRPBdILrGtXkc9lf"
  },
  {
    "code": "4ElSiY6VNWQLkZydFgnzDr",
    "url": "https://chat.whatsapp.com/4ElSiY6VNWQLkZydFgnzDr"
  },
  {
    "code": "LxoNfS9gvf2Go3OrVtFuxy",
    "url": "https://chat.whatsapp.com/LxoNfS9gvf2Go3OrVtFuxy"
  },
  {
    "code": "EApqwjdCqRK1THDdf3laHu",
    "url": "https://chat.whatsapp.com/EApqwjdCqRK1THDdf3laHu"
  },
  {
    "code": "HWV4JKqn1iMKJQlQ0ccDYe",
    "url": "https://chat.whatsapp.com/HWV4JKqn1iMKJQlQ0ccDYe"
  },
  {
    "code": "CXETrxdsrvtIbm0mVZI9oi",
    "url": "https://chat.whatsapp.com/invite/CXETrxdsrvtIbm0mVZI9oi"
  },
  {
    "code": "CVQ9N6xcoHP94NEAmdEsX3",
    "url": "https://chat.whatsapp.com/invite/CVQ9N6xcoHP94NEAmdEsX3"
  },
  {
    "code": "EM14lDqWSP837VzLWtS4OH",
    "url": "https://chat.whatsapp.com/invite/EM14lDqWSP837VzLWtS4OH"
  },
  {
    "code": "IQV3LMZG3FtD41nr8mA04Q",
    "url": "https://chat.whatsapp.com/invite/IQV3LMZG3FtD41nr8mA04Q"
  },
  {
    "code": "FZBdRugTOIO74NCpk8j8S7",
    "url": "https://chat.whatsapp.com/invite/FZBdRugTOIO74NCpk8j8S7"
  },
  {
    "code": "HnypiDSdlZILdbCpDlNt3x",
    "url": "https://chat.whatsapp.com/invite/HnypiDSdlZILdbCpDlNt3x"
  },
  {
    "code": "E6hMysQY0Dt1bRDXZrKyco",
    "url": "https://chat.whatsapp.com/invite/E6hMysQY0Dt1bRDXZrKyco"
  },
  {
    "code": "FGu1UYH2lwSLH7hWkgvioB",
    "url": "https://chat.whatsapp.com/invite/FGu1UYH2lwSLH7hWkgvioB"
  },
  {
    "code": "HBC78Rxgix82bpD7Z0uc31",
    "url": "https://chat.whatsapp.com/invite/HBC78Rxgix82bpD7Z0uc31"
  },
  {
    "code": "JOpqO63DBDVCKEXCldEkwU",
    "url": "https://chat.whatsapp.com/invite/JOpqO63DBDVCKEXCldEkwU"
  },
  {
    "code": "KOyjN2bVOXK5YndQhrUQd7",
    "url": "https://chat.whatsapp.com/invite/KOyjN2bVOXK5YndQhrUQd7"
  },
  {
    "code": "Jjzxpr6FmpA6ZeyKdLrlzg",
    "url": "https://chat.whatsapp.com/invite/Jjzxpr6FmpA6ZeyKdLrlzg"
  },
  {
    "code": "L0oH2Y3W712Il2Xuc01Vs9",
    "url": "https://chat.whatsapp.com/invite/L0oH2Y3W712Il2Xuc01Vs9"
  },
  {
    "code": "Gx6pHY1QyaALikb0M5af2f",
    "url": "https://chat.whatsapp.com/invite/Gx6pHY1QyaALikb0M5af2f"
  },
  {
    "code": "HaZbPuc6Vo03B1I81kREeN",
    "url": "https://chat.whatsapp.com/invite/HaZbPuc6Vo03B1I81kREeN"
  },
  {
    "code": "ClcbNKHSmln6I7xCEtH4FX",
    "url": "https://chat.whatsapp.com/invite/ClcbNKHSmln6I7xCEtH4FX"
  },
  {
    "code": "I6ZSYTmJzle0heTzBcX23I",
    "url": "https://chat.whatsapp.com/invite/I6ZSYTmJzle0heTzBcX23I"
  },
  {
    "code": "KGiNjsIJhUnECzm2Qd6XLQ",
    "url": "https://chat.whatsapp.com/invite/KGiNjsIJhUnECzm2Qd6XLQ"
  },
  {
    "code": "D2OPKowCZsx4zf7980teAC",
    "url": "https://chat.whatsapp.com/D2OPKowCZsx4zf7980teAC"
  },
  {
    "code": "FIPMstKWZmq9c6nubjhzxw",
    "url": "https://chat.whatsapp.com/FIPMstKWZmq9c6nubjhzxw"
  },
  {
    "code": "JFkI2KL7WkxHMw8CPcFdrA",
    "url": "https://chat.whatsapp.com/JFkI2KL7WkxHMw8CPcFdrA"
  },
  {
    "code": "LYAzZ6o096E1cn5AOMGmTQ",
    "url": "https://chat.whatsapp.com/LYAzZ6o096E1cn5AOMGmTQ"
  },
  {
    "code": "Izx8v1whFxUAKUJV5v4hLE",
    "url": "https://chat.whatsapp.com/invite/Izx8v1whFxUAKUJV5v4hLE"
  },
  {
    "code": "Hk861z4SSh5LeK5nnLNeSX",
    "url": "https://chat.whatsapp.com/Hk861z4SSh5LeK5nnLNeSX"
  },
  {
    "code": "IjbJNsVITtDF1KXHUcgma9",
    "url": "https://chat.whatsapp.com/invite/IjbJNsVITtDF1KXHUcgma9"
  },
  {
    "code": "FlQREBzpUkGCqauDraGk79",
    "url": "https://chat.whatsapp.com/invite/FlQREBzpUkGCqauDraGk79"
  },
  {
    "code": "Kd83sORjVEM7eXEF6SrDHW",
    "url": "https://chat.whatsapp.com/invite/Kd83sORjVEM7eXEF6SrDHW"
  },
  {
    "code": "DGkzNwg9RDH8FiGF7xTJ2P",
    "url": "https://chat.whatsapp.com/invite/DGkzNwg9RDH8FiGF7xTJ2P"
  },
  {
    "code": "KemhsUlOJlLLHng0dBoAVy",
    "url": "https://chat.whatsapp.com/invite/KemhsUlOJlLLHng0dBoAVy"
  },
  {
    "code": "E5N0OkzqZ9wEPNU9gBirdy",
    "url": "https://chat.whatsapp.com/invite/E5N0OkzqZ9wEPNU9gBirdy"
  },
  {
    "code": "HaHqBkNb3HjLQVlUD7keZl",
    "url": "https://chat.whatsapp.com/invite/HaHqBkNb3HjLQVlUD7keZl"
  },
  {
    "code": "BeRAQMYlBi6ETYAkFHSIUO",
    "url": "https://chat.whatsapp.com/invite/BeRAQMYlBi6ETYAkFHSIUO"
  },
  {
    "code": "HEXY1YIFgJBCuQlj1fsVbd",
    "url": "https://chat.whatsapp.com/invite/HEXY1YIFgJBCuQlj1fsVbd"
  },
  {
    "code": "HTdtGd4qpvqGJtsre0zhHj",
    "url": "https://chat.whatsapp.com/invite/HTdtGd4qpvqGJtsre0zhHj"
  },
  {
    "code": "GiOUx02GsKt42GYJB5lUxA",
    "url": "https://chat.whatsapp.com/invite/GiOUx02GsKt42GYJB5lUxA"
  },
  {
    "code": "CD47VN9CWgNBfCimutOjK9",
    "url": "https://chat.whatsapp.com/invite/CD47VN9CWgNBfCimutOjK9"
  },
  {
    "code": "ElZI4gcf8BfHSOhQOfyXFG",
    "url": "https://chat.whatsapp.com/invite/ElZI4gcf8BfHSOhQOfyXFG"
  },
  {
    "code": "5fNRShe1jP6LdqR79WSk1O",
    "url": "https://chat.whatsapp.com/invite/5fNRShe1jP6LdqR79WSk1O"
  },
  {
    "code": "KWLxmMANQGJETJzkDqGpJ5",
    "url": "https://chat.whatsapp.com/invite/KWLxmMANQGJETJzkDqGpJ5"
  },
  {
    "code": "DjzM3u1mpStIvnodfYlt47",
    "url": "https://chat.whatsapp.com/invite/DjzM3u1mpStIvnodfYlt47"
  },
  {
    "code": "LQZKCNawlxC61FuYUzbKpv",
    "url": "https://chat.whatsapp.com/LQZKCNawlxC61FuYUzbKpv"
  },
  {
    "code": "C4QMq7Cg4MKDvSLshHxCGj",
    "url": "https://chat.whatsapp.com/C4QMq7Cg4MKDvSLshHxCGj"
  },
  {
    "code": "HwxyvKOFnMG5QbuXthRseU",
    "url": "https://chat.whatsapp.com/HwxyvKOFnMG5QbuXthRseU"
  },
  {
    "code": "IaAgnvV934v0cFC7TONfPp",
    "url": "https://chat.whatsapp.com/IaAgnvV934v0cFC7TONfPp"
  },
  {
    "code": "I3YF7TwPUrv3ulppcqBcTs",
    "url": "https://chat.whatsapp.com/I3YF7TwPUrv3ulppcqBcTs"
  },
  {
    "code": "D8MupDTst4Z3hWIOlExaib",
    "url": "https://chat.whatsapp.com/D8MupDTst4Z3hWIOlExaib"
  },
  {
    "code": "DMlx1uy509u2ZsY1cT48Di",
    "url": "https://chat.whatsapp.com/DMlx1uy509u2ZsY1cT48Di"
  },
  {
    "code": "K1QjYRX15jqIR6RducGsbL",
    "url": "https://chat.whatsapp.com/K1QjYRX15jqIR6RducGsbL"
  },
  {
    "code": "JNKWcskppgpJywccHWyogt",
    "url": "https://chat.whatsapp.com/JNKWcskppgpJywccHWyogt"
  },
  {
    "code": "Iqr1GGxjSFH6KihNDVlzss",
    "url": "https://chat.whatsapp.com/Iqr1GGxjSFH6KihNDVlzss"
  },
  {
    "code": "EedDxeCQVH0BtibrUojW6J",
    "url": "https://chat.whatsapp.com/EedDxeCQVH0BtibrUojW6J"
  },
  {
    "code": "LnXTSIbDsID0fBObklAhB0",
    "url": "https://chat.whatsapp.com/LnXTSIbDsID0fBObklAhB0"
  },
  {
    "code": "I8qg5xH5KE7BYXjWEKP1Wo",
    "url": "https://chat.whatsapp.com/I8qg5xH5KE7BYXjWEKP1Wo"
  },
  {
    "code": "G8pAgKdZzWX9UdEFQC39e5",
    "url": "https://chat.whatsapp.com/G8pAgKdZzWX9UdEFQC39e5"
  },
  {
    "code": "J9yVdof0GFc1LSfWsvo7wx",
    "url": "https://chat.whatsapp.com/J9yVdof0GFc1LSfWsvo7wx"
  },
  {
    "code": "IVXndk9DCbwGS7g6sNf9CP",
    "url": "https://chat.whatsapp.com/IVXndk9DCbwGS7g6sNf9CP"
  },
  {
    "code": "KP4X9kf7TrAHyDQ3kYZhV9",
    "url": "https://chat.whatsapp.com/KP4X9kf7TrAHyDQ3kYZhV9"
  },
  {
    "code": "IozpeRyMzEJKMdZPZyhEhZ",
    "url": "https://chat.whatsapp.com/IozpeRyMzEJKMdZPZyhEhZ"
  },
  {
    "code": "FdVmmicFfvm2GpkymmV5vJ",
    "url": "https://chat.whatsapp.com/FdVmmicFfvm2GpkymmV5vJ"
  },
  {
    "code": "ETWzOF322eh6YgiD1Y0cXY",
    "url": "https://chat.whatsapp.com/ETWzOF322eh6YgiD1Y0cXY"
  },
  {
    "code": "Bl9j5APV40VL88QwjIIZKd",
    "url": "https://chat.whatsapp.com/Bl9j5APV40VL88QwjIIZKd"
  },
  {
    "code": "DjXLxFcZCzm1SbDOW6ToOB",
    "url": "https://chat.whatsapp.com/DjXLxFcZCzm1SbDOW6ToOB"
  },
  {
    "code": "Dvwh9NiVWjrIGm0tghnZO3",
    "url": "https://chat.whatsapp.com/invite/Dvwh9NiVWjrIGm0tghnZO3"
  },
  {
    "code": "DbAOuAiqR2sKmYCACzz1Vv",
    "url": "https://chat.whatsapp.com/DbAOuAiqR2sKmYCACzz1Vv"
  },
  {
    "code": "FhvovwaAhtDFzyVLrr3bHj",
    "url": "https://chat.whatsapp.com/FhvovwaAhtDFzyVLrr3bHj"
  },
  {
    "code": "BvTm00Dzlf93jPEPJy8K6Q",
    "url": "https://chat.whatsapp.com/BvTm00Dzlf93jPEPJy8K6Q"
  },
  {
    "code": "GNpibkwqMHTIlpcFIGEvlQ",
    "url": "https://chat.whatsapp.com/invite/GNpibkwqMHTIlpcFIGEvlQ"
  },
  {
    "code": "CuK2AxIMX5JCoksCPWeu2t",
    "url": "https://chat.whatsapp.com/CuK2AxIMX5JCoksCPWeu2t"
  },
  {
    "code": "KPtHyLGFqTTF4cdS26h9bq",
    "url": "https://chat.whatsapp.com/KPtHyLGFqTTF4cdS26h9bq"
  },
  {
    "code": "Fbg5qXTNIKsFvqJI4D1RPw",
    "url": "https://chat.whatsapp.com/Fbg5qXTNIKsFvqJI4D1RPw"
  },
  {
    "code": "JsAU6T7rA1yCP6oFZjVU27",
    "url": "https://chat.whatsapp.com/JsAU6T7rA1yCP6oFZjVU27"
  },
  {
    "code": "Lu3Whj2dKwMJ8pwPdl79KJ",
    "url": "https://chat.whatsapp.com/Lu3Whj2dKwMJ8pwPdl79KJ"
  },
  {
    "code": "0Wbpi4BTeln7Aqt5Y4YoH6",
    "url": "https://chat.whatsapp.com/0Wbpi4BTeln7Aqt5Y4YoH6"
  },
  {
    "code": "HIgSJgP8KZbJcuIW1OQ7LC",
    "url": "https://chat.whatsapp.com/invite/HIgSJgP8KZbJcuIW1OQ7LC"
  },
  {
    "code": "EW6Q26wukAsAEgYWznSfPT",
    "url": "https://chat.whatsapp.com/EW6Q26wukAsAEgYWznSfPT"
  },
  {
    "code": "DL2s4AlpCY57cF69ch9t96",
    "url": "https://chat.whatsapp.com/DL2s4AlpCY57cF69ch9t96"
  },
  {
    "code": "GpEcnDnizB0EsWAqZSvSmJ",
    "url": "https://chat.whatsapp.com/GpEcnDnizB0EsWAqZSvSmJ"
  },
  {
    "code": "AG51a5I1JlC6FoLaP01XG8",
    "url": "https://chat.whatsapp.com/AG51a5I1JlC6FoLaP01XG8"
  },
  {
    "code": "LhCZqPIqRyX6W4xh4K9N4W",
    "url": "https://chat.whatsapp.com/LhCZqPIqRyX6W4xh4K9N4W"
  },
  {
    "code": "L4ZgrALHfx2KpCt7TAIiz6",
    "url": "https://chat.whatsapp.com/L4ZgrALHfx2KpCt7TAIiz6"
  },
  {
    "code": "DbQZVPpRQnK7sDHgyhtPMn",
    "url": "https://chat.whatsapp.com/DbQZVPpRQnK7sDHgyhtPMn"
  },
  {
    "code": "FPTVyGD02oqIHDmGtUyrzO",
    "url": "https://chat.whatsapp.com/invite/FPTVyGD02oqIHDmGtUyrzO"
  },
  {
    "code": "BkasZj6irDX2kKkfZxXBy0",
    "url": "https://chat.whatsapp.com/invite/BkasZj6irDX2kKkfZxXBy0"
  },
  {
    "code": "Jq6vYOpNva423ywK5756iD",
    "url": "https://chat.whatsapp.com/invite/Jq6vYOpNva423ywK5756iD"
  },
  {
    "code": "KdRmtp2clQJBTydRp1kicU",
    "url": "https://chat.whatsapp.com/invite/KdRmtp2clQJBTydRp1kicU"
  },
  {
    "code": "L88yH5uxPvWEqsBcaRhDHS",
    "url": "https://chat.whatsapp.com/invite/L88yH5uxPvWEqsBcaRhDHS"
  },
  {
    "code": "8khUzgwzBgK4ci1TE74J0D",
    "url": "https://chat.whatsapp.com/invite/8khUzgwzBgK4ci1TE74J0D"
  },
  {
    "code": "FY4YXLm5RVg8CtNwbMSWge",
    "url": "https://chat.whatsapp.com/invite/FY4YXLm5RVg8CtNwbMSWge"
  },
  {
    "code": "IJ8EFME4qdAHlZRbmzDxM7",
    "url": "https://chat.whatsapp.com/invite/IJ8EFME4qdAHlZRbmzDxM7"
  },
  {
    "code": "LSbOgnjV1XX9rBtNcLH1Ke",
    "url": "https://chat.whatsapp.com/invite/LSbOgnjV1XX9rBtNcLH1Ke"
  },
  {
    "code": "IEXqtSIR7ND0OWwddXurSv",
    "url": "https://chat.whatsapp.com/invite/IEXqtSIR7ND0OWwddXurSv"
  },
  {
    "code": "BkZH8mG9o0iAZj9YrCeqr0",
    "url": "https://chat.whatsapp.com/invite/BkZH8mG9o0iAZj9YrCeqr0"
  },
  {
    "code": "DYF1AZbkmDs78L0LGYHSR8",
    "url": "https://chat.whatsapp.com/invite/DYF1AZbkmDs78L0LGYHSR8"
  },
  {
    "code": "DW3jFLACweUE3qqkxtuMOM",
    "url": "https://chat.whatsapp.com/invite/DW3jFLACweUE3qqkxtuMOM"
  },
  {
    "code": "L6bMxxqxC8RL9Me1N0OKbO",
    "url": "https://chat.whatsapp.com/invite/L6bMxxqxC8RL9Me1N0OKbO"
  },
  {
    "code": "DoLb8m9X0zgAQerQHULiHp",
    "url": "https://chat.whatsapp.com/invite/DoLb8m9X0zgAQerQHULiHp"
  },
  {
    "code": "FMtAsGEkNiz0mHdijZO4vT",
    "url": "https://chat.whatsapp.com/invite/FMtAsGEkNiz0mHdijZO4vT"
  },
  {
    "code": "EdZ9zkGuOv5DEKW5rNhf7j",
    "url": "https://chat.whatsapp.com/invite/EdZ9zkGuOv5DEKW5rNhf7j"
  },
  {
    "code": "ByNPQPWMJE2630q9saKGsS",
    "url": "https://chat.whatsapp.com/invite/ByNPQPWMJE2630q9saKGsS"
  },
  {
    "code": "FulMDkUcPNoJeizslC3qDc",
    "url": "https://chat.whatsapp.com/invite/FulMDkUcPNoJeizslC3qDc"
  },
  {
    "code": "JhYG6d2yGHpJRdNnkkqZvU",
    "url": "https://chat.whatsapp.com/invite/JhYG6d2yGHpJRdNnkkqZvU"
  },
  {
    "code": "G8ONNTlC8gxC4oegpoxe2g",
    "url": "https://chat.whatsapp.com/invite/G8ONNTlC8gxC4oegpoxe2g"
  },
  {
    "code": "FJbF6mMaS2C0moeR4ueHzB",
    "url": "https://chat.whatsapp.com/invite/FJbF6mMaS2C0moeR4ueHzB"
  },
  {
    "code": "FFxLHoAhU4g7hQklFCFK6U",
    "url": "https://chat.whatsapp.com/invite/FFxLHoAhU4g7hQklFCFK6U"
  },
  {
    "code": "KQaOWgrFxB4D7BHBqaz0W8",
    "url": "https://chat.whatsapp.com/invite/KQaOWgrFxB4D7BHBqaz0W8"
  },
  {
    "code": "HvdpKrKjSVX6Wy32YaSvZJ",
    "url": "https://chat.whatsapp.com/invite/HvdpKrKjSVX6Wy32YaSvZJ"
  },
  {
    "code": "HgsyBTNbQi3IIB98f2Ecrk",
    "url": "https://chat.whatsapp.com/invite/HgsyBTNbQi3IIB98f2Ecrk"
  },
  {
    "code": "DatFYyUpYQK2VdHgahwzup",
    "url": "https://chat.whatsapp.com/invite/DatFYyUpYQK2VdHgahwzup"
  },
  {
    "code": "JRmojQGiWCXBsv3tKI5QSZ",
    "url": "https://chat.whatsapp.com/invite/JRmojQGiWCXBsv3tKI5QSZ"
  },
  {
    "code": "JmLjAwgivRx1fmrGME5ndy",
    "url": "https://chat.whatsapp.com/invite/JmLjAwgivRx1fmrGME5ndy"
  },
  {
    "code": "Cc1WcPMS1hnFVLOnUvkUkc",
    "url": "https://chat.whatsapp.com/invite/Cc1WcPMS1hnFVLOnUvkUkc"
  },
  {
    "code": "I3BextQmqwGKVNSWA6oc5p",
    "url": "https://chat.whatsapp.com/invite/I3BextQmqwGKVNSWA6oc5p"
  },
  {
    "code": "I34bk5cHD3jAUVdYYENO5J",
    "url": "https://chat.whatsapp.com/invite/I34bk5cHD3jAUVdYYENO5J"
  },
  {
    "code": "Lrx4jOAVfC0B2TlNna6ly7",
    "url": "https://chat.whatsapp.com/invite/Lrx4jOAVfC0B2TlNna6ly7"
  },
  {
    "code": "L0hD2IINnbE5bT69t5AW7n",
    "url": "https://chat.whatsapp.com/invite/L0hD2IINnbE5bT69t5AW7n"
  },
  {
    "code": "HFkDDr4djK54nAPG199ZqM",
    "url": "https://chat.whatsapp.com/invite/HFkDDr4djK54nAPG199ZqM"
  },
  {
    "code": "HeUL6NGCIy6BoCWnCo0wyP",
    "url": "https://chat.whatsapp.com/invite/HeUL6NGCIy6BoCWnCo0wyP"
  },
  {
    "code": "CX63FZiqaIhDYAD6hOmqEu",
    "url": "https://chat.whatsapp.com/invite/CX63FZiqaIhDYAD6hOmqEu"
  },
  {
    "code": "CRm0IFMr5yKHiDzNoelEVG",
    "url": "https://chat.whatsapp.com/invite/CRm0IFMr5yKHiDzNoelEVG"
  },
  {
    "code": "JOAjqSEPiXBEEVW0iq7Ftt",
    "url": "https://chat.whatsapp.com/invite/JOAjqSEPiXBEEVW0iq7Ftt"
  },
  {
    "code": "DvRgvayPtyJHDyyEtDcpEP",
    "url": "https://chat.whatsapp.com/invite/DvRgvayPtyJHDyyEtDcpEP"
  },
  {
    "code": "B9nYtH5FfvT2CvzYPSY1jg",
    "url": "https://chat.whatsapp.com/B9nYtH5FfvT2CvzYPSY1jg"
  },
  {
    "code": "4H0HRIJgjzoEb3f6XrnR54",
    "url": "https://chat.whatsapp.com/invite/4H0HRIJgjzoEb3f6XrnR54"
  },
  {
    "code": "HiNoke9eboE4fbEwS8voQg",
    "url": "https://chat.whatsapp.com/invite/HiNoke9eboE4fbEwS8voQg"
  },
  {
    "code": "CEuZ9RqVzeaJKGffmJYm9n",
    "url": "https://chat.whatsapp.com/invite/CEuZ9RqVzeaJKGffmJYm9n"
  },
  {
    "code": "KCajuSRhjMNA9ggb6PwHs0",
    "url": "https://chat.whatsapp.com/invite/KCajuSRhjMNA9ggb6PwHs0"
  },
  {
    "code": "GR4Im1Mv5L6IzQ8KMkfoV8",
    "url": "https://chat.whatsapp.com/invite/GR4Im1Mv5L6IzQ8KMkfoV8"
  },
  {
    "code": "HVm3YigowjU2aMmkEyhGVV",
    "url": "https://chat.whatsapp.com/invite/HVm3YigowjU2aMmkEyhGVV"
  },
  {
    "code": "HEIJ2LDxA1oB30Na56Mqqb",
    "url": "https://chat.whatsapp.com/invite/HEIJ2LDxA1oB30Na56Mqqb"
  },
  {
    "code": "Eo10eb3JPkRB4U0GA0UNUq",
    "url": "https://chat.whatsapp.com/invite/Eo10eb3JPkRB4U0GA0UNUq"
  },
  {
    "code": "EFY8CdZXigiFniG4pGZ3ZM",
    "url": "https://chat.whatsapp.com/invite/EFY8CdZXigiFniG4pGZ3ZM"
  },
  {
    "code": "Jbz035cLT2eCH9abgMwzUk",
    "url": "https://chat.whatsapp.com/invite/Jbz035cLT2eCH9abgMwzUk"
  },
  {
    "code": "CeshB8lg3ptH1SIP7c9uUi",
    "url": "https://chat.whatsapp.com/invite/CeshB8lg3ptH1SIP7c9uUi"
  },
  {
    "code": "IXuON82ISf04gakHnn6SrB",
    "url": "https://chat.whatsapp.com/invite/IXuON82ISf04gakHnn6SrB"
  },
  {
    "code": "JlmRjpJ0h4mCQtiLwrNMcT",
    "url": "https://chat.whatsapp.com/invite/JlmRjpJ0h4mCQtiLwrNMcT"
  },
  {
    "code": "CBdyMMzLkMyLKK4MymvWwf",
    "url": "https://chat.whatsapp.com/invite/CBdyMMzLkMyLKK4MymvWwf"
  },
  {
    "code": "JMwGiMpyoV09gydD49yHGl",
    "url": "https://chat.whatsapp.com/invite/JMwGiMpyoV09gydD49yHGl"
  },
  {
    "code": "6eBGHtrL7q03MOZxBqJcJw",
    "url": "https://chat.whatsapp.com/invite/6eBGHtrL7q03MOZxBqJcJw"
  },
  {
    "code": "CEmMj6hfVH56pY83PHhEBe",
    "url": "https://chat.whatsapp.com/invite/CEmMj6hfVH56pY83PHhEBe"
  },
  {
    "code": "I3HMoAkASLaFYbDJ78Md2i",
    "url": "https://chat.whatsapp.com/invite/I3HMoAkASLaFYbDJ78Md2i"
  },
  {
    "code": "IxW3Ojqn2K9IOoX1FbzAwO",
    "url": "https://chat.whatsapp.com/invite/IxW3Ojqn2K9IOoX1FbzAwO"
  },
  {
    "code": "Eg2HeBMpn38DkePjVOvtei",
    "url": "https://chat.whatsapp.com/invite/Eg2HeBMpn38DkePjVOvtei"
  },
  {
    "code": "KT3WfiyrGIwKNM8qydOjjd",
    "url": "https://chat.whatsapp.com/invite/KT3WfiyrGIwKNM8qydOjjd"
  },
  {
    "code": "JhR8xP6eZWyHg0NlhBI6Le",
    "url": "https://chat.whatsapp.com/invite/JhR8xP6eZWyHg0NlhBI6Le"
  },
  {
    "code": "HIqQHUMPBi655w2NUJgGFA",
    "url": "https://chat.whatsapp.com/invite/HIqQHUMPBi655w2NUJgGFA"
  },
  {
    "code": "CdcADTU2Iq8DXa2ffFJCi0",
    "url": "https://chat.whatsapp.com/invite/CdcADTU2Iq8DXa2ffFJCi0"
  },
  {
    "code": "E7Kh1tjJO9xAdRvVOD8Mgo",
    "url": "https://chat.whatsapp.com/invite/E7Kh1tjJO9xAdRvVOD8Mgo"
  },
  {
    "code": "EVwuiIAtbwl82YURraZJfa",
    "url": "https://chat.whatsapp.com/invite/EVwuiIAtbwl82YURraZJfa"
  },
  {
    "code": "F7CfNBGOsrLC7MUqMY4uWX",
    "url": "https://chat.whatsapp.com/invite/F7CfNBGOsrLC7MUqMY4uWX"
  },
  {
    "code": "JwKlybllKX36pGieDO7LiA",
    "url": "https://chat.whatsapp.com/invite/JwKlybllKX36pGieDO7LiA"
  },
  {
    "code": "Iu2LUySiLRQJXsE4ff52J4",
    "url": "https://chat.whatsapp.com/invite/Iu2LUySiLRQJXsE4ff52J4"
  },
  {
    "code": "J5RQookyAbz2cBHMUL8AtV",
    "url": "https://chat.whatsapp.com/invite/J5RQookyAbz2cBHMUL8AtV"
  },
  {
    "code": "Gcm6VIdDIZB3Lz7Ssyfaj3",
    "url": "https://chat.whatsapp.com/invite/Gcm6VIdDIZB3Lz7Ssyfaj3"
  },
  {
    "code": "KStI1CWwy42DZSBRNkSYUV",
    "url": "https://chat.whatsapp.com/invite/KStI1CWwy42DZSBRNkSYUV"
  },
  {
    "code": "C0clYdeBjAjBS3EWrAeekH",
    "url": "https://chat.whatsapp.com/invite/C0clYdeBjAjBS3EWrAeekH"
  },
  {
    "code": "CVGOtPTjLgFHt3QLtlLVPS",
    "url": "https://chat.whatsapp.com/invite/CVGOtPTjLgFHt3QLtlLVPS"
  },
  {
    "code": "IQrnd3oUTKU700t6VYOLlE",
    "url": "https://chat.whatsapp.com/invite/IQrnd3oUTKU700t6VYOLlE"
  },
  {
    "code": "I3TDwjnnUPLIW2vYXHB4jI",
    "url": "https://chat.whatsapp.com/invite/I3TDwjnnUPLIW2vYXHB4jI"
  },
  {
    "code": "EePFGdMU6OCISGu6GGHfPM",
    "url": "https://chat.whatsapp.com/invite/EePFGdMU6OCISGu6GGHfPM"
  },
  {
    "code": "Ca2HIKaoVzoGDGTIcEVGpP",
    "url": "https://chat.whatsapp.com/invite/Ca2HIKaoVzoGDGTIcEVGpP"
  },
  {
    "code": "GtmUsQjLubDCocYZvGU7Ov",
    "url": "https://chat.whatsapp.com/invite/GtmUsQjLubDCocYZvGU7Ov"
  },
  {
    "code": "AWiRorgMgAcBJYgvaQjGcM",
    "url": "https://chat.whatsapp.com/invite/AWiRorgMgAcBJYgvaQjGcM"
  },
  {
    "code": "J2pjMTzhv95IzuFhloWORP",
    "url": "https://chat.whatsapp.com/invite/J2pjMTzhv95IzuFhloWORP"
  },
  {
    "code": "FjcNxU4E9sTEYSbT1QxNrn",
    "url": "https://chat.whatsapp.com/invite/FjcNxU4E9sTEYSbT1QxNrn"
  },
  {
    "code": "COqCOOHWTaEJ3SAwxwGx09",
    "url": "https://chat.whatsapp.com/invite/COqCOOHWTaEJ3SAwxwGx09"
  },
  {
    "code": "Ki0WWCPQ7vc1EirrzmIXjS",
    "url": "https://chat.whatsapp.com/invite/Ki0WWCPQ7vc1EirrzmIXjS"
  },
  {
    "code": "HmNa9bgGXPSHc9kKnIbgg6",
    "url": "https://chat.whatsapp.com/invite/HmNa9bgGXPSHc9kKnIbgg6"
  },
  {
    "code": "H3f6oqAG3GBBryPvpE7kO0",
    "url": "https://chat.whatsapp.com/invite/H3f6oqAG3GBBryPvpE7kO0"
  },
  {
    "code": "Ehk7KHQ0vjz4wgqbhjBhau",
    "url": "https://chat.whatsapp.com/invite/Ehk7KHQ0vjz4wgqbhjBhau"
  },
  {
    "code": "LTUdWB4Jug4Io1OJqAMDlS",
    "url": "https://chat.whatsapp.com/invite/LTUdWB4Jug4Io1OJqAMDlS"
  },
  {
    "code": "FuML027Sc2h55G8Ek8hVXk",
    "url": "https://chat.whatsapp.com/invite/FuML027Sc2h55G8Ek8hVXk"
  },
  {
    "code": "GQmH9K8JvtO1VX8Y2N0kHg",
    "url": "https://chat.whatsapp.com/invite/GQmH9K8JvtO1VX8Y2N0kHg"
  },
  {
    "code": "I5RgaPdVnP2JpURv9yk8gN",
    "url": "https://chat.whatsapp.com/invite/I5RgaPdVnP2JpURv9yk8gN"
  },
  {
    "code": "EuYw4FPkOvaCEVfRTuzKLg",
    "url": "https://chat.whatsapp.com/invite/EuYw4FPkOvaCEVfRTuzKLg"
  },
  {
    "code": "BZVcCOZUPvxAUxo3qzQPcF",
    "url": "https://chat.whatsapp.com/invite/BZVcCOZUPvxAUxo3qzQPcF"
  },
  {
    "code": "Fr4IDxSPJnX1naEdZRbRfS",
    "url": "https://chat.whatsapp.com/invite/Fr4IDxSPJnX1naEdZRbRfS"
  },
  {
    "code": "KNBwg8Qhyzz3ppp1kku1f1",
    "url": "https://chat.whatsapp.com/invite/KNBwg8Qhyzz3ppp1kku1f1"
  },
  {
    "code": "CqvchoCJORP2cdlMMp0ngp",
    "url": "https://chat.whatsapp.com/invite/CqvchoCJORP2cdlMMp0ngp"
  },
  {
    "code": "IvysxWBf8nGKSm6y8KwcBD",
    "url": "https://chat.whatsapp.com/invite/IvysxWBf8nGKSm6y8KwcBD"
  },
  {
    "code": "HBN30Uniaw8Cdywxe6XEe0",
    "url": "https://chat.whatsapp.com/invite/HBN30Uniaw8Cdywxe6XEe0"
  },
  {
    "code": "FUYaQXGm2YL5dJi7H9FmqQ",
    "url": "https://chat.whatsapp.com/invite/FUYaQXGm2YL5dJi7H9FmqQ"
  },
  {
    "code": "CJhp3jRnSMQ3uhIulQBYGq",
    "url": "https://chat.whatsapp.com/invite/CJhp3jRnSMQ3uhIulQBYGq"
  },
  {
    "code": "CWYgWhrRmM0Ep9F89uyYTf",
    "url": "https://chat.whatsapp.com/invite/CWYgWhrRmM0Ep9F89uyYTf"
  },
  {
    "code": "LG10P3OaBo6J10C5ETqTVa",
    "url": "https://chat.whatsapp.com/invite/LG10P3OaBo6J10C5ETqTVa"
  },
  {
    "code": "KfB8AbmSK2J6eb1i0Bkkxs",
    "url": "https://chat.whatsapp.com/invite/KfB8AbmSK2J6eb1i0Bkkxs"
  },
  {
    "code": "Earsjkd8B0HIMPelNgboTx",
    "url": "https://chat.whatsapp.com/invite/Earsjkd8B0HIMPelNgboTx"
  },
  {
    "code": "Hot6onu32ElHrs2MXup6WM",
    "url": "https://chat.whatsapp.com/invite/Hot6onu32ElHrs2MXup6WM"
  },
  {
    "code": "LtsrkIZfIkjJRywckcKOnM",
    "url": "https://chat.whatsapp.com/invite/LtsrkIZfIkjJRywckcKOnM"
  },
  {
    "code": "HbZnQOLSQ1t1l2Rx8M84xJ",
    "url": "https://chat.whatsapp.com/invite/HbZnQOLSQ1t1l2Rx8M84xJ"
  },
  {
    "code": "EtcDk2zC0WC81hpWsMingK",
    "url": "https://chat.whatsapp.com/invite/EtcDk2zC0WC81hpWsMingK"
  },
  {
    "code": "J4M4DDV0KOl8HvbncoYhBr",
    "url": "https://chat.whatsapp.com/invite/J4M4DDV0KOl8HvbncoYhBr"
  },
  {
    "code": "G9ATEcdLUKRA7QxbkGSVqF",
    "url": "https://chat.whatsapp.com/invite/G9ATEcdLUKRA7QxbkGSVqF"
  },
  {
    "code": "I79mcoArHCQ8Q3ipPaxANE",
    "url": "https://chat.whatsapp.com/invite/I79mcoArHCQ8Q3ipPaxANE"
  },
  {
    "code": "FVR5qoMjYsECWTkNZX8ezC",
    "url": "https://chat.whatsapp.com/invite/FVR5qoMjYsECWTkNZX8ezC"
  },
  {
    "code": "HEZ0MZyq5VPI5iRpclOoeY",
    "url": "https://chat.whatsapp.com/invite/HEZ0MZyq5VPI5iRpclOoeY"
  },
  {
    "code": "IXTKNx2cHzy2Yym79ay0Fl",
    "url": "https://chat.whatsapp.com/invite/IXTKNx2cHzy2Yym79ay0Fl"
  },
  {
    "code": "H0wjR9M1130CC3vQURjd37",
    "url": "https://chat.whatsapp.com/invite/H0wjR9M1130CC3vQURjd37"
  },
  {
    "code": "KCAAw1XH1ut4002WwGE5Xo",
    "url": "https://chat.whatsapp.com/invite/KCAAw1XH1ut4002WwGE5Xo"
  },
  {
    "code": "KLuGgCXrF4nIOhReP3QmTv",
    "url": "https://chat.whatsapp.com/invite/KLuGgCXrF4nIOhReP3QmTv"
  },
  {
    "code": "C7FYOCbwj5n58phAF8A5lu",
    "url": "https://chat.whatsapp.com/invite/C7FYOCbwj5n58phAF8A5lu"
  },
  {
    "code": "DLONJF3BMXgIpmVNHK0DOP",
    "url": "https://chat.whatsapp.com/invite/DLONJF3BMXgIpmVNHK0DOP"
  },
  {
    "code": "Gga3qPudS794jn5sDfq5Sg",
    "url": "https://chat.whatsapp.com/invite/Gga3qPudS794jn5sDfq5Sg"
  },
  {
    "code": "LdRBBn1WZc5FjviMyEniJ6",
    "url": "https://chat.whatsapp.com/invite/LdRBBn1WZc5FjviMyEniJ6"
  },
  {
    "code": "LrpOGrXIe7p43mYT1msM43",
    "url": "https://chat.whatsapp.com/invite/LrpOGrXIe7p43mYT1msM43"
  },
  {
    "code": "L446XmvACShBa9zgLHVxhv",
    "url": "https://chat.whatsapp.com/invite/L446XmvACShBa9zgLHVxhv"
  },
  {
    "code": "B5htcHYWKHVGAuMpb5XFVj",
    "url": "https://chat.whatsapp.com/invite/B5htcHYWKHVGAuMpb5XFVj"
  },
  {
    "code": "FKZ1XSLF3vW4VTFPLnfd46",
    "url": "https://chat.whatsapp.com/invite/FKZ1XSLF3vW4VTFPLnfd46"
  },
  {
    "code": "HLSA0AOyxnCDico6Y729TR",
    "url": "https://chat.whatsapp.com/invite/HLSA0AOyxnCDico6Y729TR"
  },
  {
    "code": "FsOYtftsFPDG0bpOeo0N2n",
    "url": "https://chat.whatsapp.com/invite/FsOYtftsFPDG0bpOeo0N2n"
  },
  {
    "code": "D3gDdhEoyg4HoSWSh6s2zQ",
    "url": "https://chat.whatsapp.com/invite/D3gDdhEoyg4HoSWSh6s2zQ"
  },
  {
    "code": "L9LqwqkNvM62D5fK4j7563",
    "url": "https://chat.whatsapp.com/invite/L9LqwqkNvM62D5fK4j7563"
  },
  {
    "code": "C4fZCR2s0YtI5JF8e2409d",
    "url": "https://chat.whatsapp.com/invite/C4fZCR2s0YtI5JF8e2409d"
  },
  {
    "code": "F4pHJB68Std09TIyZdjfNR",
    "url": "https://chat.whatsapp.com/invite/F4pHJB68Std09TIyZdjfNR"
  },
  {
    "code": "LEU7E7GzQoT1oFF6vGhmfy",
    "url": "https://chat.whatsapp.com/invite/LEU7E7GzQoT1oFF6vGhmfy"
  },
  {
    "code": "CWPkx8YjsRe4irqcWn2I76",
    "url": "https://chat.whatsapp.com/invite/CWPkx8YjsRe4irqcWn2I76"
  },
  {
    "code": "DXMwanwZSBI1qWxjVgbRJ3",
    "url": "https://chat.whatsapp.com/invite/DXMwanwZSBI1qWxjVgbRJ3"
  },
  {
    "code": "JTC4OSYQ3BRFGM2QAPaKNF",
    "url": "https://chat.whatsapp.com/invite/JTC4OSYQ3BRFGM2QAPaKNF"
  },
  {
    "code": "HxmL5m4L3XoB98E4iEGndR",
    "url": "https://chat.whatsapp.com/invite/HxmL5m4L3XoB98E4iEGndR"
  },
  {
    "code": "K5Qo6bQaSys4zJW9iIpFSI",
    "url": "https://chat.whatsapp.com/invite/K5Qo6bQaSys4zJW9iIpFSI"
  },
  {
    "code": "DN4iaawv01A0PFJtu8ORg5",
    "url": "https://chat.whatsapp.com/invite/DN4iaawv01A0PFJtu8ORg5"
  },
  {
    "code": "D4i6b1K0SX9EBQfrPZ9DHA",
    "url": "https://chat.whatsapp.com/invite/D4i6b1K0SX9EBQfrPZ9DHA"
  },
  {
    "code": "BYgzkefOEN7IyjjB3W5MMl",
    "url": "https://chat.whatsapp.com/invite/BYgzkefOEN7IyjjB3W5MMl"
  },
  {
    "code": "KYZoeevKZAI4gMMMIcB3xd",
    "url": "https://chat.whatsapp.com/invite/KYZoeevKZAI4gMMMIcB3xd"
  },
  {
    "code": "HAGF0dPcoeaGPyza7G3WiG",
    "url": "https://chat.whatsapp.com/invite/HAGF0dPcoeaGPyza7G3WiG"
  },
  {
    "code": "JXCjSOKRRdvDoDUYeB6reM",
    "url": "https://chat.whatsapp.com/invite/JXCjSOKRRdvDoDUYeB6reM"
  },
  {
    "code": "K0X3C15Gu6eJm6caOMbv1g",
    "url": "https://chat.whatsapp.com/invite/K0X3C15Gu6eJm6caOMbv1g"
  },
  {
    "code": "FNqqbT0SxGo1ZVM9kObELV",
    "url": "https://chat.whatsapp.com/invite/FNqqbT0SxGo1ZVM9kObELV"
  },
  {
    "code": "K4o3cu9CehqFNgcbH3gs4S",
    "url": "https://chat.whatsapp.com/invite/K4o3cu9CehqFNgcbH3gs4S"
  },
  {
    "code": "FY09pXosXRJEbrLEHlUUaU",
    "url": "https://chat.whatsapp.com/invite/FY09pXosXRJEbrLEHlUUaU"
  },
  {
    "code": "GK2Bqkoaz7R15xweTFOt6J",
    "url": "https://chat.whatsapp.com/invite/GK2Bqkoaz7R15xweTFOt6J"
  },
  {
    "code": "F3zert1c0rL6VXpLL8fpb7",
    "url": "https://chat.whatsapp.com/invite/F3zert1c0rL6VXpLL8fpb7"
  },
  {
    "code": "DaK4WZEh0wh7EfieIaux1E",
    "url": "https://chat.whatsapp.com/invite/DaK4WZEh0wh7EfieIaux1E"
  },
  {
    "code": "HF9zvWgVKb3LiMZQMALunZ",
    "url": "https://chat.whatsapp.com/invite/HF9zvWgVKb3LiMZQMALunZ"
  },
  {
    "code": "CORXlb14JazEhbunaaChz3",
    "url": "https://chat.whatsapp.com/invite/CORXlb14JazEhbunaaChz3"
  },
  {
    "code": "FJ4rt8k2uRB0O5paCWAcJp",
    "url": "https://chat.whatsapp.com/invite/FJ4rt8k2uRB0O5paCWAcJp"
  },
  {
    "code": "IW5D9WeTZp08MD6PTa5dAr",
    "url": "https://chat.whatsapp.com/invite/IW5D9WeTZp08MD6PTa5dAr"
  },
  {
    "code": "CKOY9X9LQrFHRN4AQlwFcT",
    "url": "https://chat.whatsapp.com/invite/CKOY9X9LQrFHRN4AQlwFcT"
  },
  {
    "code": "KiO0Tnsz08QJvKqbGBmMhu",
    "url": "https://chat.whatsapp.com/invite/KiO0Tnsz08QJvKqbGBmMhu"
  },
  {
    "code": "KDuXyPFCi618oQjSOR0zoA",
    "url": "https://chat.whatsapp.com/invite/KDuXyPFCi618oQjSOR0zoA"
  },
  {
    "code": "JZcITBqQwrfCyHgDwXvKLv",
    "url": "https://chat.whatsapp.com/invite/JZcITBqQwrfCyHgDwXvKLv"
  },
  {
    "code": "EzozyKssygD6b9OlxJC90U",
    "url": "https://chat.whatsapp.com/invite/EzozyKssygD6b9OlxJC90U"
  },
  {
    "code": "Epd7Np8pCScGCq4ttSH2b2",
    "url": "https://chat.whatsapp.com/invite/Epd7Np8pCScGCq4ttSH2b2"
  },
  {
    "code": "HkaCoAqDfY7LGWQcNOINoL",
    "url": "https://chat.whatsapp.com/invite/HkaCoAqDfY7LGWQcNOINoL"
  },
  {
    "code": "HlQJq6BWJSyELnzdOa3wCE",
    "url": "https://chat.whatsapp.com/invite/HlQJq6BWJSyELnzdOa3wCE"
  }
]