{
	"id": "0PnzY4KpXmkC6Rb",
	"json": "{\"id\":\"0PnzY4KpXmkC6Rb\",\"url\":\"http://findgroups.net/post/NGu8L/cryptoinfo\",\"uniqueKey\":\"http://findgroups.net/post/NGu8L/cryptoinfo\",\"method\":\"GET\",\"noRetry\":false,\"retryCount\":0,\"errorMessages\":[],\"headers\":{},\"userData\":{\"__crawlee\":{\"enqueueStrategy\":\"same-domain\"}}}",
	"method": "GET",
	"orderNo": 1743749066104,
	"retryCount": 0,
	"uniqueKey": "http://findgroups.net/post/NGu8L/cryptoinfo",
	"url": "http://findgroups.net/post/NGu8L/cryptoinfo"
}