{
	"id": "0toPsXDJP2FMr7D",
	"json": "{\"id\":\"0toPsXDJP2FMr7D\",\"url\":\"https://adulto.grupos.top/grupodeputaria/FsRNIeotvcUDXb42Zm2ltQ\",\"uniqueKey\":\"https://adulto.grupos.top/grupodeputaria/FsRNIeotvcUDXb42Zm2ltQ\",\"method\":\"GET\",\"noRetry\":false,\"retryCount\":0,\"errorMessages\":[],\"headers\":{},\"userData\":{\"__crawlee\":{\"enqueueStrategy\":\"same-domain\"}}}",
	"method": "GET",
	"orderNo": 1743749046668,
	"retryCount": 0,
	"uniqueKey": "https://adulto.grupos.top/grupodeputaria/FsRNIeotvcUDXb42Zm2ltQ",
	"url": "https://adulto.grupos.top/grupodeputaria/FsRNIeotvcUDXb42Zm2ltQ"
}