{
	"id": "0WLpStr2ochOmrl",
	"json": "{\"id\":\"0WLpStr2ochOmrl\",\"url\":\"http://findgroups.net/category-dtl/sports-lovers\",\"loadedUrl\":\"http://findgroups.net/category-dtl/sports-lovers\",\"uniqueKey\":\"http://findgroups.net/category-dtl/sports-lovers\",\"method\":\"GET\",\"noRetry\":false,\"retryCount\":0,\"errorMessages\":[],\"headers\":{},\"userData\":{\"__crawlee\":{\"enqueueStrategy\":\"same-domain\",\"state\":4}},\"handledAt\":\"2025-04-04T06:43:56.236Z\"}",
	"method": "GET",
	"orderNo": null,
	"retryCount": 0,
	"uniqueKey": "http://findgroups.net/category-dtl/sports-lovers",
	"url": "http://findgroups.net/category-dtl/sports-lovers"
}