{
	"id": "2bdg4gsRfADXwNK",
	"json": "{\"id\":\"2bdg4gsRfADXwNK\",\"url\":\"https://realgrouplinks.com/tag/Malaya-Groups/\",\"uniqueKey\":\"https://realgrouplinks.com/tag/Malaya-Groups\",\"method\":\"GET\",\"noRetry\":false,\"retryCount\":0,\"errorMessages\":[],\"headers\":{},\"userData\":{\"__crawlee\":{\"enqueueStrategy\":\"same-domain\"}}}",
	"method": "GET",
	"orderNo": 1743749003048,
	"retryCount": 0,
	"uniqueKey": "https://realgrouplinks.com/tag/Malaya-Groups",
	"url": "https://realgrouplinks.com/tag/Malaya-Groups/"
}