{
	"id": "2Hm9nk92agoRdWF",
	"json": "{\"id\":\"2Hm9nk92agoRdWF\",\"url\":\"https://findgrouplinks.com/commerce-whatsapp-group-link/\",\"uniqueKey\":\"https://findgrouplinks.com/commerce-whatsapp-group-link\",\"method\":\"GET\",\"noRetry\":false,\"retryCount\":0,\"errorMessages\":[],\"headers\":{},\"userData\":{\"__crawlee\":{\"enqueueStrategy\":\"same-domain\"}}}",
	"method": "GET",
	"orderNo": 1743749446839,
	"retryCount": 0,
	"uniqueKey": "https://findgrouplinks.com/commerce-whatsapp-group-link",
	"url": "https://findgrouplinks.com/commerce-whatsapp-group-link/"
}