{
	"id": "3TZqNeQeR2X9pgA",
	"json": "{\"id\":\"3TZqNeQeR2X9pgA\",\"url\":\"https://www.bestsexxxporn.com/vid-5Qzh-beaitifil-bhabi-geting-msg-frm-drivr.html\",\"uniqueKey\":\"https://www.bestsexxxporn.com/vid-5Qzh-beaitifil-bhabi-geting-msg-frm-drivr.html\",\"method\":\"GET\",\"noRetry\":false,\"retryCount\":0,\"errorMessages\":[],\"headers\":{},\"userData\":{\"__crawlee\":{\"enqueueStrategy\":\"same-domain\"}}}",
	"method": "GET",
	"orderNo": 1743749013058,
	"retryCount": 0,
	"uniqueKey": "https://www.bestsexxxporn.com/vid-5Qzh-beaitifil-bhabi-geting-msg-frm-drivr.html",
	"url": "https://www.bestsexxxporn.com/vid-5Qzh-beaitifil-bhabi-geting-msg-frm-drivr.html"
}