{
	"id": "4Wz0ik4Aco1eBzG",
	"json": "{\"id\":\"4Wz0ik4Aco1eBzG\",\"url\":\"http://findgroups.net/post/h2Rjt/sunyb-cs-fall17-yocket\",\"uniqueKey\":\"http://findgroups.net/post/h2Rjt/sunyb-cs-fall17-yocket\",\"method\":\"GET\",\"noRetry\":false,\"retryCount\":0,\"errorMessages\":[],\"headers\":{},\"userData\":{\"__crawlee\":{\"enqueueStrategy\":\"same-domain\"}}}",
	"method": "GET",
	"orderNo": 1743749128252,
	"retryCount": 0,
	"uniqueKey": "http://findgroups.net/post/h2Rjt/sunyb-cs-fall17-yocket",
	"url": "http://findgroups.net/post/h2Rjt/sunyb-cs-fall17-yocket"
}