{
	"id": "8OHBst5tCQRXhkA",
	"json": "{\"id\":\"8OHBst5tCQRXhkA\",\"url\":\"http://findgroups.net/post/4qPA0/das-ist-berlin-gruppe\",\"uniqueKey\":\"http://findgroups.net/post/4qPA0/das-ist-berlin-gruppe\",\"method\":\"GET\",\"noRetry\":false,\"retryCount\":0,\"errorMessages\":[],\"headers\":{},\"userData\":{\"__crawlee\":{\"enqueueStrategy\":\"same-domain\"}}}",
	"method": "GET",
	"orderNo": 1743749127042,
	"retryCount": 0,
	"uniqueKey": "http://findgroups.net/post/4qPA0/das-ist-berlin-gruppe",
	"url": "http://findgroups.net/post/4qPA0/das-ist-berlin-gruppe"
}