{
	"id": "9cOrbgUIIYLXMSE",
	"json": "{\"id\":\"9cOrbgUIIYLXMSE\",\"url\":\"https://mbwhatsking.com/category/guide/\",\"uniqueKey\":\"https://mbwhatsking.com/category/guide\",\"method\":\"GET\",\"noRetry\":false,\"retryCount\":0,\"errorMessages\":[],\"headers\":{},\"userData\":{\"__crawlee\":{\"enqueueStrategy\":\"same-domain\"}}}",
	"method": "GET",
	"orderNo": 1743749004158,
	"retryCount": 0,
	"uniqueKey": "https://mbwhatsking.com/category/guide",
	"url": "https://mbwhatsking.com/category/guide/"
}