{
	"id": "9SqSPaMAYlVNeXq",
	"json": "{\"id\":\"9SqSPaMAYlVNeXq\",\"url\":\"https://adulto.grupos.top/whatsapp-porno/coroas/?page=4\",\"uniqueKey\":\"https://adulto.grupos.top/whatsapp-porno/coroas?page=4\",\"method\":\"GET\",\"noRetry\":false,\"retryCount\":0,\"errorMessages\":[],\"headers\":{},\"userData\":{\"__crawlee\":{\"enqueueStrategy\":\"same-domain\"}}}",
	"method": "GET",
	"orderNo": 1743749045123,
	"retryCount": 0,
	"uniqueKey": "https://adulto.grupos.top/whatsapp-porno/coroas?page=4",
	"url": "https://adulto.grupos.top/whatsapp-porno/coroas/?page=4"
}