{
	"id": "a1HcAEX9VUBLGSL",
	"json": "{\"id\":\"a1HcAEX9VUBLGSL\",\"url\":\"https://www.liveinternet.ru/users/lomovolga/\",\"uniqueKey\":\"https://www.liveinternet.ru/users/lomovolga\",\"method\":\"GET\",\"noRetry\":false,\"retryCount\":0,\"errorMessages\":[],\"headers\":{},\"userData\":{\"__crawlee\":{\"enqueueStrategy\":\"same-domain\"}}}",
	"method": "GET",
	"orderNo": 1743749043191,
	"retryCount": 0,
	"uniqueKey": "https://www.liveinternet.ru/users/lomovolga",
	"url": "https://www.liveinternet.ru/users/lomovolga/"
}