{
	"id": "ACPENUbbsthS7ep",
	"json": "{\"id\":\"ACPENUbbsthS7ep\",\"url\":\"https://okporn.xxx/search/REBECCA%27S-BIG-COCK-PORN/\",\"uniqueKey\":\"https://okporn.xxx/search/REBECCA%27S-BIG-COCK-PORN\",\"method\":\"GET\",\"noRetry\":false,\"retryCount\":0,\"errorMessages\":[],\"headers\":{},\"userData\":{\"__crawlee\":{\"enqueueStrategy\":\"same-domain\"}}}",
	"method": "GET",
	"orderNo": 1743749028536,
	"retryCount": 0,
	"uniqueKey": "https://okporn.xxx/search/REBECCA%27S-BIG-COCK-PORN",
	"url": "https://okporn.xxx/search/REBECCA%27S-BIG-COCK-PORN/"
}