{
	"id": "An8XOYphS60MajU",
	"json": "{\"id\":\"An8XOYphS60MajU\",\"url\":\"https://thewhatsappgrouplink.com/haiti-whatsapp-group-2025/\",\"uniqueKey\":\"https://thewhatsappgrouplink.com/haiti-whatsapp-group-2025\",\"method\":\"GET\",\"noRetry\":false,\"retryCount\":0,\"errorMessages\":[],\"headers\":{},\"userData\":{\"__crawlee\":{\"enqueueStrategy\":\"same-domain\"}}}",
	"method": "GET",
	"orderNo": 1743749006218,
	"retryCount": 0,
	"uniqueKey": "https://thewhatsappgrouplink.com/haiti-whatsapp-group-2025",
	"url": "https://thewhatsappgrouplink.com/haiti-whatsapp-group-2025/"
}