{
	"id": "ApWjIsX5DFGZNHl",
	"json": "{\"id\":\"ApWjIsX5DFGZNHl\",\"url\":\"https://en.groupio.app/group/join/Muslim-Dunya-Khabar-27287\",\"loadedUrl\":\"https://en.groupio.app/group/join/Muslim-Dunya-Khabar-27287\",\"uniqueKey\":\"https://en.groupio.app/group/join/Muslim-Dunya-Khabar-27287\",\"method\":\"GET\",\"noRetry\":false,\"retryCount\":0,\"errorMessages\":[],\"headers\":{},\"userData\":{\"__crawlee\":{\"enqueueStrategy\":\"same-domain\",\"state\":4}},\"handledAt\":\"2025-04-04T06:49:15.323Z\"}",
	"method": "GET",
	"orderNo": null,
	"retryCount": 0,
	"uniqueKey": "https://en.groupio.app/group/join/Muslim-Dunya-Khabar-27287",
	"url": "https://en.groupio.app/group/join/Muslim-Dunya-Khabar-27287"
}