{
	"id": "ASDXIHdA2ETcr06",
	"json": "{\"id\":\"ASDXIHdA2ETcr06\",\"url\":\"https://adulto.grupos.top/whatsapp-porno/porno/\",\"loadedUrl\":\"https://adulto.grupos.top/whatsapp-porno/porno/\",\"uniqueKey\":\"https://adulto.grupos.top/whatsapp-porno/porno\",\"method\":\"GET\",\"noRetry\":false,\"retryCount\":0,\"errorMessages\":[],\"headers\":{},\"userData\":{\"__crawlee\":{\"enqueueStrategy\":\"same-domain\",\"state\":4}},\"handledAt\":\"2025-04-04T06:45:28.920Z\"}",
	"method": "GET",
	"orderNo": null,
	"retryCount": 0,
	"uniqueKey": "https://adulto.grupos.top/whatsapp-porno/porno",
	"url": "https://adulto.grupos.top/whatsapp-porno/porno/"
}