{
	"id": "aTQoXL31wwyNNm3",
	"json": "{\"id\":\"aTQoXL31wwyNNm3\",\"url\":\"https://wappgroups.com/indian-whatsapp-group-links/\",\"uniqueKey\":\"https://wappgroups.com/indian-whatsapp-group-links\",\"method\":\"GET\",\"noRetry\":false,\"retryCount\":0,\"errorMessages\":[],\"headers\":{},\"userData\":{\"__crawlee\":{\"enqueueStrategy\":\"same-domain\"}}}",
	"method": "GET",
	"orderNo": 1743749006089,
	"retryCount": 0,
	"uniqueKey": "https://wappgroups.com/indian-whatsapp-group-links",
	"url": "https://wappgroups.com/indian-whatsapp-group-links/"
}