{
	"id": "AV5hAoFxgOjlXrF",
	"json": "{\"id\":\"AV5hAoFxgOjlXrF\",\"url\":\"https://forum.lingq.com/t/%D0%BE-%D0%B2%D1%80%D0%B5%D0%BC%D0%B5%D0%BD%D0%B8-%D0%B8-%D0%BE-%D1%81%D0%B5%D0%B1%D0%B5-%D0%B6%D0%B8%D0%BB%D0%B8%D1%89%D0%BD%D1%8B%D0%B5-%D1%83%D1%81%D0%BB%D0%BE%D0%B2%D0%B8%D1%8F-%D0%B2-%D1%80%D0%BE%D1%81%D1%81%D0%B8%D0%B8-about-the-time-and-myself-the-living-conditions-in-russia/58685\",\"uniqueKey\":\"https://forum.lingq.com/t/%D0%BE-%D0%B2%D1%80%D0%B5%D0%BC%D0%B5%D0%BD%D0%B8-%D0%B8-%D0%BE-%D1%81%D0%B5%D0%B1%D0%B5-%D0%B6%D0%B8%D0%BB%D0%B8%D1%89%D0%BD%D1%8B%D0%B5-%D1%83%D1%81%D0%BB%D0%BE%D0%B2%D0%B8%D1%8F-%D0%B2-%D1%80%D0%BE%D1%81%D1%81%D0%B8%D0%B8-about-the-time-and-myself-the-living-conditions-in-russia/58685\",\"method\":\"GET\",\"noRetry\":false,\"retryCount\":0,\"errorMessages\":[],\"headers\":{},\"userData\":{\"__crawlee\":{\"enqueueStrategy\":\"same-domain\"}}}",
	"method": "GET",
	"orderNo": 1743749373479,
	"retryCount": 0,
	"uniqueKey": "https://forum.lingq.com/t/%D0%BE-%D0%B2%D1%80%D0%B5%D0%BC%D0%B5%D0%BD%D0%B8-%D0%B8-%D0%BE-%D1%81%D0%B5%D0%B1%D0%B5-%D0%B6%D0%B8%D0%BB%D0%B8%D1%89%D0%BD%D1%8B%D0%B5-%D1%83%D1%81%D0%BB%D0%BE%D0%B2%D0%B8%D1%8F-%D0%B2-%D1%80%D0%BE%D1%81%D1%81%D0%B8%D0%B8-about-the-time-and-myself-the-living-conditions-in-russia/58685",
	"url": "https://forum.lingq.com/t/%D0%BE-%D0%B2%D1%80%D0%B5%D0%BC%D0%B5%D0%BD%D0%B8-%D0%B8-%D0%BE-%D1%81%D0%B5%D0%B1%D0%B5-%D0%B6%D0%B8%D0%BB%D0%B8%D1%89%D0%BD%D1%8B%D0%B5-%D1%83%D1%81%D0%BB%D0%BE%D0%B2%D0%B8%D1%8F-%D0%B2-%D1%80%D0%BE%D1%81%D1%81%D0%B8%D0%B8-about-the-time-and-myself-the-living-conditions-in-russia/58685"
}