{
	"id": "bECF6LEjC4ljaMQ",
	"json": "{\"id\":\"bECF6LEjC4ljaMQ\",\"url\":\"https://whatsagrouplinks.com/tips-memilih-situs-judi-bola-resmi/\",\"uniqueKey\":\"https://whatsagrouplinks.com/tips-memilih-situs-judi-bola-resmi\",\"method\":\"GET\",\"noRetry\":false,\"retryCount\":0,\"errorMessages\":[],\"headers\":{},\"userData\":{\"__crawlee\":{\"enqueueStrategy\":\"same-domain\"}}}",
	"method": "GET",
	"orderNo": 1743749007731,
	"retryCount": 0,
	"uniqueKey": "https://whatsagrouplinks.com/tips-memilih-situs-judi-bola-resmi",
	"url": "https://whatsagrouplinks.com/tips-memilih-situs-judi-bola-resmi/"
}