{
	"id": "Bz2QQ5u6KVHVZ66",
	"json": "{\"id\":\"Bz2QQ5u6KVHVZ66\",\"url\":\"https://findgrouplinks.com/justin-bieber-whatsapp-group-link/\",\"uniqueKey\":\"https://findgrouplinks.com/justin-bieber-whatsapp-group-link\",\"method\":\"GET\",\"noRetry\":false,\"retryCount\":0,\"errorMessages\":[],\"headers\":{},\"userData\":{\"__crawlee\":{\"enqueueStrategy\":\"same-domain\"}}}",
	"method": "GET",
	"orderNo": 1743749057997,
	"retryCount": 0,
	"uniqueKey": "https://findgrouplinks.com/justin-bieber-whatsapp-group-link",
	"url": "https://findgrouplinks.com/justin-bieber-whatsapp-group-link/"
}