{
	"id": "ciK6w2mztZBniZD",
	"json": "{\"id\":\"ciK6w2mztZBniZD\",\"url\":\"https://groupio.app/group/join/Hentai-group-7048\",\"uniqueKey\":\"https://groupio.app/group/join/Hentai-group-7048\",\"method\":\"GET\",\"noRetry\":false,\"retryCount\":0,\"errorMessages\":[],\"headers\":{},\"userData\":{\"__crawlee\":{\"enqueueStrategy\":\"same-domain\"}}}",
	"method": "GET",
	"orderNo": 1743749308819,
	"retryCount": 0,
	"uniqueKey": "https://groupio.app/group/join/Hentai-group-7048",
	"url": "https://groupio.app/group/join/Hentai-group-7048"
}