{
	"id": "doiehXgTZhY5zWW",
	"json": "{\"id\":\"doiehXgTZhY5zWW\",\"url\":\"https://wa.waziper.com/germany-whatsapp-group-links\",\"uniqueKey\":\"https://wa.waziper.com/germany-whatsapp-group-links\",\"method\":\"GET\",\"noRetry\":false,\"retryCount\":0,\"errorMessages\":[],\"headers\":{},\"userData\":{\"__crawlee\":{\"enqueueStrategy\":\"same-domain\"}}}",
	"method": "GET",
	"orderNo": 1743749007875,
	"retryCount": 0,
	"uniqueKey": "https://wa.waziper.com/germany-whatsapp-group-links",
	"url": "https://wa.waziper.com/germany-whatsapp-group-links"
}