{
	"id": "dp2IIuTdAmp9gJp",
	"json": "{\"id\":\"dp2IIuTdAmp9gJp\",\"url\":\"https://forum.lingq.com/c/learning-hebrew-forum-ask-a-tutor/55\",\"uniqueKey\":\"https://forum.lingq.com/c/learning-hebrew-forum-ask-a-tutor/55\",\"method\":\"GET\",\"noRetry\":false,\"retryCount\":0,\"errorMessages\":[],\"headers\":{},\"userData\":{\"__crawlee\":{\"enqueueStrategy\":\"same-domain\"}}}",
	"method": "GET",
	"orderNo": 1743748995414,
	"retryCount": 0,
	"uniqueKey": "https://forum.lingq.com/c/learning-hebrew-forum-ask-a-tutor/55",
	"url": "https://forum.lingq.com/c/learning-hebrew-forum-ask-a-tutor/55"
}