{
	"id": "DsYz1dAPebYmJ9A",
	"json": "{\"id\":\"DsYz1dAPebYmJ9A\",\"url\":\"https://www.nairaland.com/8388345/god-put-efccs-most-wanted\",\"uniqueKey\":\"https://www.nairaland.com/8388345/god-put-efccs-most-wanted\",\"method\":\"GET\",\"noRetry\":false,\"retryCount\":0,\"errorMessages\":[],\"headers\":{},\"userData\":{\"__crawlee\":{\"enqueueStrategy\":\"same-domain\"}}}",
	"method": "GET",
	"orderNo": 1743749018010,
	"retryCount": 0,
	"uniqueKey": "https://www.nairaland.com/8388345/god-put-efccs-most-wanted",
	"url": "https://www.nairaland.com/8388345/god-put-efccs-most-wanted"
}