{
	"id": "efeE3DXCRTbjDM8",
	"json": "{\"id\":\"efeE3DXCRTbjDM8\",\"url\":\"https://groupsgenie.com/page/contact-us\",\"uniqueKey\":\"https://groupsgenie.com/page/contact-us\",\"method\":\"GET\",\"noRetry\":false,\"retryCount\":0,\"errorMessages\":[],\"headers\":{},\"userData\":{\"__crawlee\":{\"enqueueStrategy\":\"same-domain\"}}}",
	"method": "GET",
	"orderNo": 1743748998555,
	"retryCount": 0,
	"uniqueKey": "https://groupsgenie.com/page/contact-us",
	"url": "https://groupsgenie.com/page/contact-us"
}