{
	"id": "F6tWjvrFM2GcmBM",
	"json": "{\"id\":\"F6tWjvrFM2GcmBM\",\"url\":\"https://appgrouplink.com/english-learning-whatsapp-group-links/\",\"loadedUrl\":\"https://appgrouplink.com/english-learning-whatsapp-group-links/\",\"uniqueKey\":\"https://appgrouplink.com/english-learning-whatsapp-group-links\",\"method\":\"GET\",\"noRetry\":false,\"retryCount\":0,\"errorMessages\":[],\"headers\":{},\"userData\":{\"__crawlee\":{\"enqueueStrategy\":\"same-domain\",\"state\":4}},\"handledAt\":\"2025-04-04T06:44:08.900Z\"}",
	"method": "GET",
	"orderNo": null,
	"retryCount": 0,
	"uniqueKey": "https://appgrouplink.com/english-learning-whatsapp-group-links",
	"url": "https://appgrouplink.com/english-learning-whatsapp-group-links/"
}