{
	"id": "Fd2SxxQj0THFmNr",
	"json": "{\"id\":\"Fd2SxxQj0THFmNr\",\"url\":\"https://thegroups.org/dp/B0D3RN5W37?ref=MarsFS_VICC_blinksqm\",\"uniqueKey\":\"https://thegroups.org/dp/B0D3RN5W37?ref=MarsFS_VICC_blinksqm\",\"method\":\"GET\",\"noRetry\":false,\"retryCount\":0,\"errorMessages\":[],\"headers\":{},\"userData\":{\"__crawlee\":{\"enqueueStrategy\":\"same-domain\"}}}",
	"method": "GET",
	"orderNo": 1743749019075,
	"retryCount": 0,
	"uniqueKey": "https://thegroups.org/dp/B0D3RN5W37?ref=MarsFS_VICC_blinksqm",
	"url": "https://thegroups.org/dp/B0D3RN5W37?ref=MarsFS_VICC_blinksqm"
}