{
	"id": "FtYkQS1kh7RIe69",
	"json": "{\"id\":\"FtYkQS1kh7RIe69\",\"url\":\"https://t.me/noelstar_tech_and_entertainment\",\"uniqueKey\":\"https://t.me/noelstar_tech_and_entertainment\",\"method\":\"GET\",\"noRetry\":false,\"retryCount\":0,\"errorMessages\":[],\"headers\":{},\"userData\":{\"__crawlee\":{\"enqueueStrategy\":\"same-domain\"}}}",
	"method": "GET",
	"orderNo": 1743749015922,
	"retryCount": 0,
	"uniqueKey": "https://t.me/noelstar_tech_and_entertainment",
	"url": "https://t.me/noelstar_tech_and_entertainment"
}