{
	"id": "g3TRUPRBEm2xkd8",
	"json": "{\"id\":\"g3TRUPRBEm2xkd8\",\"url\":\"http://findgroups.net/post/k7QGV/mrearn-earn-money\",\"uniqueKey\":\"http://findgroups.net/post/k7QGV/mrearn-earn-money\",\"method\":\"GET\",\"noRetry\":false,\"retryCount\":0,\"errorMessages\":[],\"headers\":{},\"userData\":{\"__crawlee\":{\"enqueueStrategy\":\"same-domain\"}}}",
	"method": "GET",
	"orderNo": 1743749128401,
	"retryCount": 0,
	"uniqueKey": "http://findgroups.net/post/k7QGV/mrearn-earn-money",
	"url": "http://findgroups.net/post/k7QGV/mrearn-earn-money"
}