{
	"id": "G9QXy7GpZo2U4Zq",
	"json": "{\"id\":\"G9QXy7GpZo2U4Zq\",\"url\":\"https://forum.lingq.com/t/englishespa%C3%B1ol/77420\",\"uniqueKey\":\"https://forum.lingq.com/t/englishespa%C3%B1ol/77420\",\"method\":\"GET\",\"noRetry\":false,\"retryCount\":0,\"errorMessages\":[],\"headers\":{},\"userData\":{\"__crawlee\":{\"enqueueStrategy\":\"same-domain\"}}}",
	"method": "GET",
	"orderNo": 1743749450331,
	"retryCount": 0,
	"uniqueKey": "https://forum.lingq.com/t/englishespa%C3%B1ol/77420",
	"url": "https://forum.lingq.com/t/englishespa%C3%B1ol/77420"
}