{
	"id": "ggR8L2Rm7EWInkF",
	"json": "{\"id\":\"ggR8L2Rm7EWInkF\",\"url\":\"https://whtsgruplinks.com/usa-whatsapp-group-links/\",\"uniqueKey\":\"https://whtsgruplinks.com/usa-whatsapp-group-links\",\"method\":\"GET\",\"noRetry\":false,\"retryCount\":0,\"errorMessages\":[],\"headers\":{},\"userData\":{\"__crawlee\":{\"enqueueStrategy\":\"same-domain\"}}}",
	"method": "GET",
	"orderNo": 1743749013347,
	"retryCount": 0,
	"uniqueKey": "https://whtsgruplinks.com/usa-whatsapp-group-links",
	"url": "https://whtsgruplinks.com/usa-whatsapp-group-links/"
}