{
	"id": "GLfqE7Oh2wzw99N",
	"json": "{\"id\":\"GLfqE7Oh2wzw99N\",\"url\":\"https://forum.lingq.com/c/%E4%B8%AD%E6%96%87%E5%85%AC%E5%BC%80%E8%AE%BA%E5%9D%9B-open-forum-in-chinese/33\",\"loadedUrl\":\"https://forum.lingq.com/c/%E4%B8%AD%E6%96%87%E5%85%AC%E5%BC%80%E8%AE%BA%E5%9D%9B-open-forum-in-chinese/33\",\"uniqueKey\":\"https://forum.lingq.com/c/%E4%B8%AD%E6%96%87%E5%85%AC%E5%BC%80%E8%AE%BA%E5%9D%9B-open-forum-in-chinese/33\",\"method\":\"GET\",\"noRetry\":false,\"retryCount\":0,\"errorMessages\":[],\"headers\":{},\"userData\":{\"__crawlee\":{\"enqueueStrategy\":\"same-domain\",\"state\":4}},\"handledAt\":\"2025-04-04T06:50:35.377Z\"}",
	"method": "GET",
	"orderNo": null,
	"retryCount": 0,
	"uniqueKey": "https://forum.lingq.com/c/%E4%B8%AD%E6%96%87%E5%85%AC%E5%BC%80%E8%AE%BA%E5%9D%9B-open-forum-in-chinese/33",
	"url": "https://forum.lingq.com/c/%E4%B8%AD%E6%96%87%E5%85%AC%E5%BC%80%E8%AE%BA%E5%9D%9B-open-forum-in-chinese/33"
}