{
	"id": "gPpzuxfJqfSOxFi",
	"json": "{\"id\":\"gPpzuxfJqfSOxFi\",\"url\":\"https://adulto.grupos.top/grupodeputaria/IEH4q8wNieFECj2M2kVNP0\",\"uniqueKey\":\"https://adulto.grupos.top/grupodeputaria/IEH4q8wNieFECj2M2kVNP0\",\"method\":\"GET\",\"noRetry\":false,\"retryCount\":0,\"errorMessages\":[],\"headers\":{},\"userData\":{\"__crawlee\":{\"enqueueStrategy\":\"same-domain\"}}}",
	"method": "GET",
	"orderNo": 1743749036413,
	"retryCount": 0,
	"uniqueKey": "https://adulto.grupos.top/grupodeputaria/IEH4q8wNieFECj2M2kVNP0",
	"url": "https://adulto.grupos.top/grupodeputaria/IEH4q8wNieFECj2M2kVNP0"
}