{
	"id": "GPZZtlvyKa9goei",
	"json": "{\"id\":\"GPZZtlvyKa9goei\",\"url\":\"https://telegram.me/AllIndiaManufacturingGroup\",\"uniqueKey\":\"https://telegram.me/AllIndiaManufacturingGroup\",\"method\":\"GET\",\"noRetry\":false,\"retryCount\":0,\"errorMessages\":[],\"headers\":{},\"userData\":{\"__crawlee\":{\"enqueueStrategy\":\"same-domain\"}}}",
	"method": "GET",
	"orderNo": 1743749016231,
	"retryCount": 0,
	"uniqueKey": "https://telegram.me/AllIndiaManufacturingGroup",
	"url": "https://telegram.me/AllIndiaManufacturingGroup"
}