{
	"id": "gSDx55dROuWFrxV",
	"json": "{\"id\":\"gSDx55dROuWFrxV\",\"url\":\"https://adulto.grupos.top/grupodeputaria/LrfwZCzgaAIHGt7L9pjgzJ\",\"uniqueKey\":\"https://adulto.grupos.top/grupodeputaria/LrfwZCzgaAIHGt7L9pjgzJ\",\"method\":\"GET\",\"noRetry\":false,\"retryCount\":0,\"errorMessages\":[],\"headers\":{},\"userData\":{\"__crawlee\":{\"enqueueStrategy\":\"same-domain\"}}}",
	"method": "GET",
	"orderNo": 1743749136329,
	"retryCount": 0,
	"uniqueKey": "https://adulto.grupos.top/grupodeputaria/LrfwZCzgaAIHGt7L9pjgzJ",
	"url": "https://adulto.grupos.top/grupodeputaria/LrfwZCzgaAIHGt7L9pjgzJ"
}