{
	"id": "GWyqYWpxsEt8WxG",
	"json": "{\"id\":\"GWyqYWpxsEt8WxG\",\"url\":\"https://forum.lingq.com/t/como-excluir-li%C3%A7%C3%A3o-do-lingq/57506\",\"uniqueKey\":\"https://forum.lingq.com/t/como-excluir-li%C3%A7%C3%A3o-do-lingq/57506\",\"method\":\"GET\",\"noRetry\":false,\"retryCount\":0,\"errorMessages\":[],\"headers\":{},\"userData\":{\"__crawlee\":{\"enqueueStrategy\":\"same-domain\"}}}",
	"method": "GET",
	"orderNo": 1743749304175,
	"retryCount": 0,
	"uniqueKey": "https://forum.lingq.com/t/como-excluir-li%C3%A7%C3%A3o-do-lingq/57506",
	"url": "https://forum.lingq.com/t/como-excluir-li%C3%A7%C3%A3o-do-lingq/57506"
}