{
	"id": "H4ZwylQ74QdpGjN",
	"json": "{\"id\":\"H4ZwylQ74QdpGjN\",\"url\":\"http://findgroups.net/post/YG6hh/singapore-jobs-tamilians\",\"uniqueKey\":\"http://findgroups.net/post/YG6hh/singapore-jobs-tamilians\",\"method\":\"GET\",\"noRetry\":false,\"retryCount\":0,\"errorMessages\":[],\"headers\":{},\"userData\":{\"__crawlee\":{\"enqueueStrategy\":\"same-domain\"}}}",
	"method": "GET",
	"orderNo": 1743749128491,
	"retryCount": 0,
	"uniqueKey": "http://findgroups.net/post/YG6hh/singapore-jobs-tamilians",
	"url": "http://findgroups.net/post/YG6hh/singapore-jobs-tamilians"
}