{
	"id": "IeTIgKPFFNLIZ9F",
	"json": "{\"id\":\"IeTIgKPFFNLIZ9F\",\"url\":\"https://www.hindustantimes.com/cities/delhi-news\",\"uniqueKey\":\"https://www.hindustantimes.com/cities/delhi-news\",\"method\":\"GET\",\"noRetry\":false,\"retryCount\":0,\"errorMessages\":[],\"headers\":{},\"userData\":{\"__crawlee\":{\"enqueueStrategy\":\"same-domain\"}}}",
	"method": "GET",
	"orderNo": 1743749017170,
	"retryCount": 0,
	"uniqueKey": "https://www.hindustantimes.com/cities/delhi-news",
	"url": "https://www.hindustantimes.com/cities/delhi-news"
}