{
	"id": "ifXlh1ly8ZFKKfS",
	"json": "{\"id\":\"ifXlh1ly8ZFKKfS\",\"url\":\"https://findgroups.net/post/wbeih/talking-point\",\"uniqueKey\":\"https://findgroups.net/post/wbeih/talking-point\",\"method\":\"GET\",\"noRetry\":false,\"retryCount\":0,\"errorMessages\":[],\"headers\":{},\"userData\":{\"__crawlee\":{\"enqueueStrategy\":\"same-domain\"}}}",
	"method": "GET",
	"orderNo": 1743749316869,
	"retryCount": 0,
	"uniqueKey": "https://findgroups.net/post/wbeih/talking-point",
	"url": "https://findgroups.net/post/wbeih/talking-point"
}