{
	"id": "iqu4hYz4hCbZhpA",
	"json": "{\"id\":\"iqu4hYz4hCbZhpA\",\"url\":\"http://findgroups.net/post/6BzcY/turkey-and-kosovo\",\"loadedUrl\":\"http://findgroups.net/post/6BzcY/turkey-and-kosovo\",\"uniqueKey\":\"http://findgroups.net/post/6BzcY/turkey-and-kosovo\",\"method\":\"GET\",\"noRetry\":false,\"retryCount\":0,\"errorMessages\":[],\"headers\":{},\"userData\":{\"__crawlee\":{\"enqueueStrategy\":\"same-domain\",\"state\":4}},\"handledAt\":\"2025-04-03T16:05:36.372Z\"}",
	"method": "GET",
	"orderNo": null,
	"retryCount": 0,
	"uniqueKey": "http://findgroups.net/post/6BzcY/turkey-and-kosovo",
	"url": "http://findgroups.net/post/6BzcY/turkey-and-kosovo"
}