{
	"id": "IUTeQGqfxc1V4mH",
	"json": "{\"id\":\"IUTeQGqfxc1V4mH\",\"url\":\"https://forum.lingq.com/t/spanish-accents/490310\",\"uniqueKey\":\"https://forum.lingq.com/t/spanish-accents/490310\",\"method\":\"GET\",\"noRetry\":false,\"retryCount\":0,\"errorMessages\":[],\"headers\":{},\"userData\":{\"__crawlee\":{\"enqueueStrategy\":\"same-domain\"}}}",
	"method": "GET",
	"orderNo": 1743749341233,
	"retryCount": 0,
	"uniqueKey": "https://forum.lingq.com/t/spanish-accents/490310",
	"url": "https://forum.lingq.com/t/spanish-accents/490310"
}