{
	"id": "kmYm07vccQSchzo",
	"json": "{\"id\":\"kmYm07vccQSchzo\",\"url\":\"https://area51.porn/tags/desi-sex-video/\",\"uniqueKey\":\"https://area51.porn/tags/desi-sex-video\",\"method\":\"GET\",\"noRetry\":false,\"retryCount\":0,\"errorMessages\":[],\"headers\":{},\"userData\":{\"__crawlee\":{\"enqueueStrategy\":\"same-domain\"}}}",
	"method": "GET",
	"orderNo": 1743749319039,
	"retryCount": 0,
	"uniqueKey": "https://area51.porn/tags/desi-sex-video",
	"url": "https://area51.porn/tags/desi-sex-video/"
}