{
	"id": "Kqi0XQGyDabX2Yo",
	"json": "{\"id\":\"Kqi0XQGyDabX2Yo\",\"url\":\"https://findgroups.net/post/nsXEK/only-study-for-students\",\"uniqueKey\":\"https://findgroups.net/post/nsXEK/only-study-for-students\",\"method\":\"GET\",\"noRetry\":false,\"retryCount\":0,\"errorMessages\":[],\"headers\":{},\"userData\":{\"__crawlee\":{\"enqueueStrategy\":\"same-domain\"}}}",
	"method": "GET",
	"orderNo": 1743749446316,
	"retryCount": 0,
	"uniqueKey": "https://findgroups.net/post/nsXEK/only-study-for-students",
	"url": "https://findgroups.net/post/nsXEK/only-study-for-students"
}