{
	"id": "kRP5go96TL6rumD",
	"json": "{\"id\":\"kRP5go96TL6rumD\",\"url\":\"https://groupsorlinks.com/country/peru-whatsapp-join-group-link\",\"uniqueKey\":\"https://groupsorlinks.com/country/peru-whatsapp-join-group-link\",\"method\":\"GET\",\"noRetry\":false,\"retryCount\":0,\"errorMessages\":[],\"headers\":{},\"userData\":{\"__crawlee\":{\"enqueueStrategy\":\"same-domain\"}}}",
	"method": "GET",
	"orderNo": 1743748998977,
	"retryCount": 0,
	"uniqueKey": "https://groupsorlinks.com/country/peru-whatsapp-join-group-link",
	"url": "https://groupsorlinks.com/country/peru-whatsapp-join-group-link"
}