{
	"id": "KxQzWoGUuev8moH",
	"json": "{\"id\":\"KxQzWoGUuev8moH\",\"url\":\"https://forum.lingq.com/t/how-to-learn-a-language-for-travel-the-dos-and-don%E2%80%99ts-the-linguist-blog/1217466\",\"uniqueKey\":\"https://forum.lingq.com/t/how-to-learn-a-language-for-travel-the-dos-and-don%E2%80%99ts-the-linguist-blog/1217466\",\"method\":\"GET\",\"noRetry\":false,\"retryCount\":0,\"errorMessages\":[],\"headers\":{},\"userData\":{\"__crawlee\":{\"enqueueStrategy\":\"same-domain\"}}}",
	"method": "GET",
	"orderNo": 1743749238742,
	"retryCount": 0,
	"uniqueKey": "https://forum.lingq.com/t/how-to-learn-a-language-for-travel-the-dos-and-don%E2%80%99ts-the-linguist-blog/1217466",
	"url": "https://forum.lingq.com/t/how-to-learn-a-language-for-travel-the-dos-and-don%E2%80%99ts-the-linguist-blog/1217466"
}