{
	"id": "lFx8rxggeZpHteR",
	"json": "{\"id\":\"lFx8rxggeZpHteR\",\"url\":\"https://area51.porn/channels/moms-bang-teens/\",\"uniqueKey\":\"https://area51.porn/channels/moms-bang-teens\",\"method\":\"GET\",\"noRetry\":false,\"retryCount\":0,\"errorMessages\":[],\"headers\":{},\"userData\":{\"__crawlee\":{\"enqueueStrategy\":\"same-domain\"}}}",
	"method": "GET",
	"orderNo": 1743749044905,
	"retryCount": 0,
	"uniqueKey": "https://area51.porn/channels/moms-bang-teens",
	"url": "https://area51.porn/channels/moms-bang-teens/"
}