{
	"id": "Lp1SPw9YytQMRF4",
	"json": "{\"id\":\"Lp1SPw9YytQMRF4\",\"url\":\"https://findgroups.net/post/cI7rh/visca-barca\",\"uniqueKey\":\"https://findgroups.net/post/cI7rh/visca-barca\",\"method\":\"GET\",\"noRetry\":false,\"retryCount\":0,\"errorMessages\":[],\"headers\":{},\"userData\":{\"__crawlee\":{\"enqueueStrategy\":\"same-domain\"}}}",
	"method": "GET",
	"orderNo": 1743749363570,
	"retryCount": 0,
	"uniqueKey": "https://findgroups.net/post/cI7rh/visca-barca",
	"url": "https://findgroups.net/post/cI7rh/visca-barca"
}