{
	"id": "Ltf5UjMLpk4Eqny",
	"json": "{\"id\":\"Ltf5UjMLpk4Eqny\",\"url\":\"https://adulto.grupos.top/telegram-putaria/vazou-na-net-18-s/\",\"uniqueKey\":\"https://adulto.grupos.top/telegram-putaria/vazou-na-net-18-s\",\"method\":\"GET\",\"noRetry\":false,\"retryCount\":0,\"errorMessages\":[],\"headers\":{},\"userData\":{\"__crawlee\":{\"enqueueStrategy\":\"same-domain\"}}}",
	"method": "GET",
	"orderNo": 1743749031532,
	"retryCount": 0,
	"uniqueKey": "https://adulto.grupos.top/telegram-putaria/vazou-na-net-18-s",
	"url": "https://adulto.grupos.top/telegram-putaria/vazou-na-net-18-s/"
}