{
	"id": "m7dX6libZK1Oyyl",
	"json": "{\"id\":\"m7dX6libZK1Oyyl\",\"url\":\"https://chat.whatsapp.com/HihSjKh8d8h4yWhLOZylEe\",\"uniqueKey\":\"https://chat.whatsapp.com/HihSjKh8d8h4yWhLOZylEe\",\"method\":\"GET\",\"noRetry\":false,\"retryCount\":0,\"errorMessages\":[],\"headers\":{},\"userData\":{\"__crawlee\":{\"enqueueStrategy\":\"same-domain\"}}}",
	"method": "GET",
	"orderNo": 1743749007930,
	"retryCount": 0,
	"uniqueKey": "https://chat.whatsapp.com/HihSjKh8d8h4yWhLOZylEe",
	"url": "https://chat.whatsapp.com/HihSjKh8d8h4yWhLOZylEe"
}