{
	"id": "Md0o7nX4AOAjD8d",
	"json": "{\"id\":\"Md0o7nX4AOAjD8d\",\"url\":\"https://findgroups.net/post/Ukpvx/uk-village\",\"uniqueKey\":\"https://findgroups.net/post/Ukpvx/uk-village\",\"method\":\"GET\",\"noRetry\":false,\"retryCount\":0,\"errorMessages\":[],\"headers\":{},\"userData\":{\"__crawlee\":{\"enqueueStrategy\":\"same-domain\"}}}",
	"method": "GET",
	"orderNo": 1743749353220,
	"retryCount": 0,
	"uniqueKey": "https://findgroups.net/post/Ukpvx/uk-village",
	"url": "https://findgroups.net/post/Ukpvx/uk-village"
}