{
	"id": "NGKBPNlnNxPqapO",
	"json": "{\"id\":\"NGKBPNlnNxPqapO\",\"url\":\"https://whatslinksonly.com/boys-whatsapp-group-links/\",\"uniqueKey\":\"https://whatslinksonly.com/boys-whatsapp-group-links\",\"method\":\"GET\",\"noRetry\":false,\"retryCount\":0,\"errorMessages\":[],\"headers\":{},\"userData\":{\"__crawlee\":{\"enqueueStrategy\":\"same-domain\"}}}",
	"method": "GET",
	"orderNo": 1743749011092,
	"retryCount": 0,
	"uniqueKey": "https://whatslinksonly.com/boys-whatsapp-group-links",
	"url": "https://whatslinksonly.com/boys-whatsapp-group-links/"
}