{
	"id": "nMU3OVJP5A73PmB",
	"json": "{\"id\":\"nMU3OVJP5A73PmB\",\"url\":\"https://whtsgrouplinks.org/asianet-news-whatsapp-group-links/\",\"uniqueKey\":\"https://whtsgrouplinks.org/asianet-news-whatsapp-group-links\",\"method\":\"GET\",\"noRetry\":false,\"retryCount\":0,\"errorMessages\":[],\"headers\":{},\"userData\":{\"__crawlee\":{\"enqueueStrategy\":\"same-domain\"}}}",
	"method": "GET",
	"orderNo": 1743749203429,
	"retryCount": 0,
	"uniqueKey": "https://whtsgrouplinks.org/asianet-news-whatsapp-group-links",
	"url": "https://whtsgrouplinks.org/asianet-news-whatsapp-group-links/"
}