{
	"id": "oI39bkPwHQxPQAQ",
	"json": "{\"id\":\"oI39bkPwHQxPQAQ\",\"url\":\"https://forum.lingq.com/u/benscheelings\",\"uniqueKey\":\"https://forum.lingq.com/u/benscheelings\",\"method\":\"GET\",\"noRetry\":false,\"retryCount\":0,\"errorMessages\":[],\"headers\":{},\"userData\":{\"__crawlee\":{\"enqueueStrategy\":\"same-domain\"}}}",
	"method": "GET",
	"orderNo": 1743749285319,
	"retryCount": 0,
	"uniqueKey": "https://forum.lingq.com/u/benscheelings",
	"url": "https://forum.lingq.com/u/benscheelings"
}