{
	"id": "oVapvu9LHshnYHz",
	"json": "{\"id\":\"oVapvu9LHshnYHz\",\"url\":\"http://findgroups.net/post/2Rnzm/online-device-sale\",\"uniqueKey\":\"http://findgroups.net/post/2Rnzm/online-device-sale\",\"method\":\"GET\",\"noRetry\":false,\"retryCount\":0,\"errorMessages\":[],\"headers\":{},\"userData\":{\"__crawlee\":{\"enqueueStrategy\":\"same-domain\"}}}",
	"method": "GET",
	"orderNo": 1743749129841,
	"retryCount": 0,
	"uniqueKey": "http://findgroups.net/post/2Rnzm/online-device-sale",
	"url": "http://findgroups.net/post/2Rnzm/online-device-sale"
}