{
	"id": "qYONDkXL17DzR1t",
	"json": "{\"id\":\"qYONDkXL17DzR1t\",\"url\":\"https://chat.whatsapp.com/Iiv8jDdaqf38poOHGEfR42\",\"uniqueKey\":\"https://chat.whatsapp.com/Iiv8jDdaqf38poOHGEfR42\",\"method\":\"GET\",\"noRetry\":false,\"retryCount\":0,\"errorMessages\":[],\"headers\":{},\"userData\":{\"__crawlee\":{\"enqueueStrategy\":\"same-domain\"}}}",
	"method": "GET",
	"orderNo": 1743748995754,
	"retryCount": 0,
	"uniqueKey": "https://chat.whatsapp.com/Iiv8jDdaqf38poOHGEfR42",
	"url": "https://chat.whatsapp.com/Iiv8jDdaqf38poOHGEfR42"
}