{
	"id": "rG6OU65fOVxpjzS",
	"json": "{\"id\":\"rG6OU65fOVxpjzS\",\"url\":\"https://tr.groupio.app/groups/allgemein\",\"uniqueKey\":\"https://tr.groupio.app/groups/allgemein\",\"method\":\"GET\",\"noRetry\":false,\"retryCount\":0,\"errorMessages\":[],\"headers\":{},\"userData\":{\"__crawlee\":{\"enqueueStrategy\":\"same-domain\"}}}",
	"method": "GET",
	"orderNo": 1743749129294,
	"retryCount": 0,
	"uniqueKey": "https://tr.groupio.app/groups/allgemein",
	"url": "https://tr.groupio.app/groups/allgemein"
}