{
	"id": "RJx3cbgwCJTLNbD",
	"json": "{\"id\":\"RJx3cbgwCJTLNbD\",\"url\":\"http://findgroups.net/post/r9cG9/chat-in-english\",\"uniqueKey\":\"http://findgroups.net/post/r9cG9/chat-in-english\",\"method\":\"GET\",\"noRetry\":false,\"retryCount\":0,\"errorMessages\":[],\"headers\":{},\"userData\":{\"__crawlee\":{\"enqueueStrategy\":\"same-domain\"}}}",
	"method": "GET",
	"orderNo": 1743696097176,
	"retryCount": 0,
	"uniqueKey": "http://findgroups.net/post/r9cG9/chat-in-english",
	"url": "http://findgroups.net/post/r9cG9/chat-in-english"
}