{
	"id": "RkvkIgsq3DyOW1g",
	"json": "{\"id\":\"RkvkIgsq3DyOW1g\",\"url\":\"https://joinwpgroups.com/category/jobs-whatsapp-group-links/\",\"uniqueKey\":\"https://joinwpgroups.com/category/jobs-whatsapp-group-links\",\"method\":\"GET\",\"noRetry\":false,\"retryCount\":0,\"errorMessages\":[],\"headers\":{},\"userData\":{\"__crawlee\":{\"enqueueStrategy\":\"same-domain\"}}}",
	"method": "GET",
	"orderNo": 1743749000464,
	"retryCount": 0,
	"uniqueKey": "https://joinwpgroups.com/category/jobs-whatsapp-group-links",
	"url": "https://joinwpgroups.com/category/jobs-whatsapp-group-links/"
}