{
	"id": "S3l9UPg1QXozvdh",
	"json": "{\"id\":\"S3l9UPg1QXozvdh\",\"url\":\"https://t.me/RAJASTHAN_Gk_Patwari_REET_EXAM\",\"uniqueKey\":\"https://t.me/RAJASTHAN_Gk_Patwari_REET_EXAM\",\"method\":\"GET\",\"noRetry\":false,\"retryCount\":0,\"errorMessages\":[],\"headers\":{},\"userData\":{\"__crawlee\":{\"enqueueStrategy\":\"same-domain\"}}}",
	"method": "GET",
	"orderNo": 1743749016487,
	"retryCount": 0,
	"uniqueKey": "https://t.me/RAJASTHAN_Gk_Patwari_REET_EXAM",
	"url": "https://t.me/RAJASTHAN_Gk_Patwari_REET_EXAM"
}