{
	"id": "sl0gCa4pkrLHzNK",
	"json": "{\"id\":\"sl0gCa4pkrLHzNK\",\"url\":\"http://findgroups.net/post/3XGki/electrical-community\",\"loadedUrl\":\"http://findgroups.net/post/3XGki/electrical-community\",\"uniqueKey\":\"http://findgroups.net/post/3XGki/electrical-community\",\"method\":\"GET\",\"noRetry\":false,\"retryCount\":0,\"errorMessages\":[],\"headers\":{},\"userData\":{\"__crawlee\":{\"enqueueStrategy\":\"same-domain\",\"state\":4}},\"handledAt\":\"2025-04-03T16:05:24.454Z\"}",
	"method": "GET",
	"orderNo": null,
	"retryCount": 0,
	"uniqueKey": "http://findgroups.net/post/3XGki/electrical-community",
	"url": "http://findgroups.net/post/3XGki/electrical-community"
}