{
	"id": "soeHaVOCpEPH1d7",
	"json": "{\"id\":\"soeHaVOCpEPH1d7\",\"url\":\"https://www.hindustantimes.com/author/ht-sports-desk-101607439300849\",\"uniqueKey\":\"https://www.hindustantimes.com/author/ht-sports-desk-101607439300849\",\"method\":\"GET\",\"noRetry\":false,\"retryCount\":0,\"errorMessages\":[],\"headers\":{},\"userData\":{\"__crawlee\":{\"enqueueStrategy\":\"same-domain\"}}}",
	"method": "GET",
	"orderNo": 1743749017241,
	"retryCount": 0,
	"uniqueKey": "https://www.hindustantimes.com/author/ht-sports-desk-101607439300849",
	"url": "https://www.hindustantimes.com/author/ht-sports-desk-101607439300849"
}