{
	"id": "TbqOdElGPiCSWyf",
	"json": "{\"id\":\"TbqOdElGPiCSWyf\",\"url\":\"https://forum.lingq.com/t/cant-read-german-books-on-lingq/968804\",\"uniqueKey\":\"https://forum.lingq.com/t/cant-read-german-books-on-lingq/968804\",\"method\":\"GET\",\"noRetry\":false,\"retryCount\":0,\"errorMessages\":[],\"headers\":{},\"userData\":{\"__crawlee\":{\"enqueueStrategy\":\"same-domain\"}}}",
	"method": "GET",
	"orderNo": 1743749303075,
	"retryCount": 0,
	"uniqueKey": "https://forum.lingq.com/t/cant-read-german-books-on-lingq/968804",
	"url": "https://forum.lingq.com/t/cant-read-german-books-on-lingq/968804"
}