{
	"id": "tlkEyTqgQp7IcKN",
	"json": "{\"id\":\"tlkEyTqgQp7IcKN\",\"url\":\"http://findgroups.net/post/AHnSi/anime-vorgruppe\",\"loadedUrl\":\"http://findgroups.net/post/AHnSi/anime-vorgruppe\",\"uniqueKey\":\"http://findgroups.net/post/AHnSi/anime-vorgruppe\",\"method\":\"GET\",\"noRetry\":false,\"retryCount\":0,\"errorMessages\":[],\"headers\":{},\"userData\":{\"__crawlee\":{\"enqueueStrategy\":\"same-domain\",\"state\":4}},\"handledAt\":\"2025-04-03T16:05:38.575Z\"}",
	"method": "GET",
	"orderNo": null,
	"retryCount": 0,
	"uniqueKey": "http://findgroups.net/post/AHnSi/anime-vorgruppe",
	"url": "http://findgroups.net/post/AHnSi/anime-vorgruppe"
}