{
	"id": "tVx5jJvawKZ9hbg",
	"json": "{\"id\":\"tVx5jJvawKZ9hbg\",\"url\":\"https://chat.whatsapp.com/LfRircmexna9wPeEw3XaPG\",\"uniqueKey\":\"https://chat.whatsapp.com/LfRircmexna9wPeEw3XaPG\",\"method\":\"GET\",\"noRetry\":false,\"retryCount\":0,\"errorMessages\":[],\"headers\":{},\"userData\":{\"__crawlee\":{\"enqueueStrategy\":\"same-domain\"}}}",
	"method": "GET",
	"orderNo": 1743748995563,
	"retryCount": 0,
	"uniqueKey": "https://chat.whatsapp.com/LfRircmexna9wPeEw3XaPG",
	"url": "https://chat.whatsapp.com/LfRircmexna9wPeEw3XaPG"
}