{
	"id": "uCct5kf2dQ2L2JU",
	"json": "{\"id\":\"uCct5kf2dQ2L2JU\",\"url\":\"https://adulto.grupos.top/whatsapp-porno/anal/?page=3\",\"uniqueKey\":\"https://adulto.grupos.top/whatsapp-porno/anal?page=3\",\"method\":\"GET\",\"noRetry\":false,\"retryCount\":0,\"errorMessages\":[],\"headers\":{},\"userData\":{\"__crawlee\":{\"enqueueStrategy\":\"same-domain\"}}}",
	"method": "GET",
	"orderNo": 1743749039029,
	"retryCount": 0,
	"uniqueKey": "https://adulto.grupos.top/whatsapp-porno/anal?page=3",
	"url": "https://adulto.grupos.top/whatsapp-porno/anal/?page=3"
}