{
	"id": "UX4Qw1Qi9IH82GW",
	"json": "{\"id\":\"UX4Qw1Qi9IH82GW\",\"url\":\"https://ankuragarwal.in/jiffy-referral-code\",\"uniqueKey\":\"https://ankuragarwal.in/jiffy-referral-code\",\"method\":\"GET\",\"noRetry\":false,\"retryCount\":0,\"errorMessages\":[],\"headers\":{},\"userData\":{\"__crawlee\":{\"enqueueStrategy\":\"same-domain\"}}}",
	"method": "GET",
	"orderNo": 1743749019396,
	"retryCount": 0,
	"uniqueKey": "https://ankuragarwal.in/jiffy-referral-code",
	"url": "https://ankuragarwal.in/jiffy-referral-code"
}