{
	"id": "VTDE7WyAO9BiX7Q",
	"json": "{\"id\":\"VTDE7WyAO9BiX7Q\",\"url\":\"https://forum.lingq.com/t/%E5%90%8D%E8%A9%9E-%E9%81%8B%E5%8B%95%E9%83%A8%E3%81%86%E3%82%93%E3%81%A9%E3%81%86%E3%81%B6-club-de-sport-%C3%A0-l%E2%80%99%C3%A9cole/52530\",\"uniqueKey\":\"https://forum.lingq.com/t/%E5%90%8D%E8%A9%9E-%E9%81%8B%E5%8B%95%E9%83%A8%E3%81%86%E3%82%93%E3%81%A9%E3%81%86%E3%81%B6-club-de-sport-%C3%A0-l%E2%80%99%C3%A9cole/52530\",\"method\":\"GET\",\"noRetry\":false,\"retryCount\":0,\"errorMessages\":[],\"headers\":{},\"userData\":{\"__crawlee\":{\"enqueueStrategy\":\"same-domain\"}}}",
	"method": "GET",
	"orderNo": 1743749300740,
	"retryCount": 0,
	"uniqueKey": "https://forum.lingq.com/t/%E5%90%8D%E8%A9%9E-%E9%81%8B%E5%8B%95%E9%83%A8%E3%81%86%E3%82%93%E3%81%A9%E3%81%86%E3%81%B6-club-de-sport-%C3%A0-l%E2%80%99%C3%A9cole/52530",
	"url": "https://forum.lingq.com/t/%E5%90%8D%E8%A9%9E-%E9%81%8B%E5%8B%95%E9%83%A8%E3%81%86%E3%82%93%E3%81%A9%E3%81%86%E3%81%B6-club-de-sport-%C3%A0-l%E2%80%99%C3%A9cole/52530"
}