{
	"id": "vuENHqBWCgu3ZJJ",
	"json": "{\"id\":\"vuENHqBWCgu3ZJJ\",\"url\":\"https://www.whatsgroup.in/forex-trading-whatsapp-group-links/\",\"uniqueKey\":\"https://www.whatsgroup.in/forex-trading-whatsapp-group-links\",\"method\":\"GET\",\"noRetry\":false,\"retryCount\":0,\"errorMessages\":[],\"headers\":{},\"userData\":{\"__crawlee\":{\"enqueueStrategy\":\"same-domain\"}}}",
	"method": "GET",
	"orderNo": 1743749024748,
	"retryCount": 0,
	"uniqueKey": "https://www.whatsgroup.in/forex-trading-whatsapp-group-links",
	"url": "https://www.whatsgroup.in/forex-trading-whatsapp-group-links/"
}