{
	"id": "VwztCdrYlg97WMX",
	"json": "{\"id\":\"VwztCdrYlg97WMX\",\"url\":\"https://www.hindustantimes.com/cricket/players/arshdeep-singh-67905\",\"uniqueKey\":\"https://www.hindustantimes.com/cricket/players/arshdeep-singh-67905\",\"method\":\"GET\",\"noRetry\":false,\"retryCount\":0,\"errorMessages\":[],\"headers\":{},\"userData\":{\"__crawlee\":{\"enqueueStrategy\":\"same-domain\"}}}",
	"method": "GET",
	"orderNo": 1743749017320,
	"retryCount": 0,
	"uniqueKey": "https://www.hindustantimes.com/cricket/players/arshdeep-singh-67905",
	"url": "https://www.hindustantimes.com/cricket/players/arshdeep-singh-67905"
}