{
	"id": "W2qU3gqXOhx29EV",
	"json": "{\"id\":\"W2qU3gqXOhx29EV\",\"url\":\"https://forum.lingq.com/t/%E8%AF%B7%E9%97%AE%E5%A6%82%E4%BD%95%E5%8F%96%E6%B6%88%E4%BB%98%E8%B4%B9%E4%BC%9A%E5%91%98%EF%BC%9F/59296\",\"uniqueKey\":\"https://forum.lingq.com/t/%E8%AF%B7%E9%97%AE%E5%A6%82%E4%BD%95%E5%8F%96%E6%B6%88%E4%BB%98%E8%B4%B9%E4%BC%9A%E5%91%98%EF%BC%9F/59296\",\"method\":\"GET\",\"noRetry\":false,\"retryCount\":0,\"errorMessages\":[],\"headers\":{},\"userData\":{\"__crawlee\":{\"enqueueStrategy\":\"same-domain\"}}}",
	"method": "GET",
	"orderNo": 1743749435353,
	"retryCount": 0,
	"uniqueKey": "https://forum.lingq.com/t/%E8%AF%B7%E9%97%AE%E5%A6%82%E4%BD%95%E5%8F%96%E6%B6%88%E4%BB%98%E8%B4%B9%E4%BC%9A%E5%91%98%EF%BC%9F/59296",
	"url": "https://forum.lingq.com/t/%E8%AF%B7%E9%97%AE%E5%A6%82%E4%BD%95%E5%8F%96%E6%B6%88%E4%BB%98%E8%B4%B9%E4%BC%9A%E5%91%98%EF%BC%9F/59296"
}