{
	"id": "WihcM6sgE4W4uuz",
	"json": "{\"id\":\"WihcM6sgE4W4uuz\",\"url\":\"https://desi.grouplinksjoin.com\",\"loadedUrl\":\"https://desi.grouplinksjoin.com/\",\"uniqueKey\":\"https://desi.grouplinksjoin.com\",\"method\":\"GET\",\"noRetry\":false,\"retryCount\":0,\"errorMessages\":[],\"headers\":{},\"userData\":{\"__crawlee\":{\"state\":4}},\"handledAt\":\"2025-04-04T06:43:13.690Z\"}",
	"method": "GET",
	"orderNo": null,
	"retryCount": 0,
	"uniqueKey": "https://desi.grouplinksjoin.com",
	"url": "https://desi.grouplinksjoin.com"
}