{
	"id": "WQgJxdKg1lLiQmB",
	"json": "{\"id\":\"WQgJxdKg1lLiQmB\",\"url\":\"https://whatsgrouplinks.org/privacy-policy/\",\"uniqueKey\":\"https://whatsgrouplinks.org/privacy-policy\",\"method\":\"GET\",\"noRetry\":false,\"retryCount\":0,\"errorMessages\":[],\"headers\":{},\"userData\":{\"__crawlee\":{\"enqueueStrategy\":\"same-domain\"}}}",
	"method": "GET",
	"orderNo": 1743749012517,
	"retryCount": 0,
	"uniqueKey": "https://whatsgrouplinks.org/privacy-policy",
	"url": "https://whatsgrouplinks.org/privacy-policy/"
}