{
	"id": "xUdNpt6nrXK18Xg",
	"json": "{\"id\":\"xUdNpt6nrXK18Xg\",\"url\":\"https://thegroups.org/dp/B086PFKYVH?ref=MarsFS_eero_AG\",\"uniqueKey\":\"https://thegroups.org/dp/B086PFKYVH?ref=MarsFS_eero_AG\",\"method\":\"GET\",\"noRetry\":false,\"retryCount\":0,\"errorMessages\":[],\"headers\":{},\"userData\":{\"__crawlee\":{\"enqueueStrategy\":\"same-domain\"}}}",
	"method": "GET",
	"orderNo": 1743749019077,
	"retryCount": 0,
	"uniqueKey": "https://thegroups.org/dp/B086PFKYVH?ref=MarsFS_eero_AG",
	"url": "https://thegroups.org/dp/B086PFKYVH?ref=MarsFS_eero_AG"
}