{
	"id": "YGiHkSa82fXEsGz",
	"json": "{\"id\":\"YGiHkSa82fXEsGz\",\"url\":\"https://whatslinkhub.com/join-british-whatsapp-group-links/\",\"uniqueKey\":\"https://whatslinkhub.com/join-british-whatsapp-group-links\",\"method\":\"GET\",\"noRetry\":false,\"retryCount\":0,\"errorMessages\":[],\"headers\":{},\"userData\":{\"__crawlee\":{\"enqueueStrategy\":\"same-domain\"}}}",
	"method": "GET",
	"orderNo": 1743749010243,
	"retryCount": 0,
	"uniqueKey": "https://whatslinkhub.com/join-british-whatsapp-group-links",
	"url": "https://whatslinkhub.com/join-british-whatsapp-group-links/"
}