{
	"id": "ZcmmQ1MQ6hYuo6V",
	"json": "{\"id\":\"ZcmmQ1MQ6hYuo6V\",\"url\":\"http://findgroups.net/post/xPgKh/landwirtschaft-gruppe\",\"uniqueKey\":\"http://findgroups.net/post/xPgKh/landwirtschaft-gruppe\",\"method\":\"GET\",\"noRetry\":false,\"retryCount\":0,\"errorMessages\":[],\"headers\":{},\"userData\":{\"__crawlee\":{\"enqueueStrategy\":\"same-domain\"}}}",
	"method": "GET",
	"orderNo": 1743696091933,
	"retryCount": 0,
	"uniqueKey": "http://findgroups.net/post/xPgKh/landwirtschaft-gruppe",
	"url": "http://findgroups.net/post/xPgKh/landwirtschaft-gruppe"
}